{"nodes": [{"id": "577528"}, {"id": "1042152"}, {"id": "1083305"}, {"id": "1197655"}, {"id": "1208008"}, {"id": "122952"}, {"id": "33707"}, {"id": "455154"}, {"id": "105732"}, {"id": "590105"}], "links": [{"source": 0, "target": 1, "value": 1}, {"source": 0, "target": 2, "value": 1}, {"source": 0, "target": 3, "value": 1}, {"source": 0, "target": 4, "value": 1}, {"source": 0, "target": 5, "value": 1}, {"source": 2, "target": 0, "value": 2}, {"source": 6, "target": 0, "value": 3}, {"source": 7, "target": 0, "value": 3}, {"source": 8, "target": 0, "value": 2}, {"source": 9, "target": 0, "value": 2}]}