{"nodes": [{"id": "1143639", "group": "7", "neighbors": ["1079396", "1312277", "1425352", "161994", "169797", "20967", "210814", "295863", "567841", "609256", "843401", "952821"]}, {"id": "1524498", "group": "7", "neighbors": ["1079396", "1143639", "1312277", "1425352", "169797", "20967", "211950", "266349", "295863", "567841", "952821"]}, {"id": "295863", "group": "7", "neighbors": ["1079396", "1143639", "1312277", "1425352", "1524498", "169797", "1770468", "20967", "210814", "211950", "266349", "567841", "609256", "843401", "952821"]}, {"id": "952821", "group": "7", "neighbors": ["1079396", "1143639", "1425352", "1524498", "169797", "20967", "210814", "295863", "567841", "609256", "843401"]}, {"id": "1770468", "group": "7", "neighbors": ["1143639", "1312277", "1425352", "1524498", "169797", "20967", "210814", "211950", "266349", "295863", "567841", "609256", "843401", "952821"]}, {"id": "266349", "group": "7", "neighbors": ["1143639"]}, {"id": "843401", "group": "7", "neighbors": ["1079396", "1143639", "1312277", "1425352", "1524498", "169797", "1770468", "20967", "210814", "211950", "266349", "295863", "567841", "609256", "952821"]}, {"id": "1079396", "group": "7", "neighbors": ["1770468", "295863"]}, {"id": "1312277", "group": "7", "neighbors": ["1770468"]}, {"id": "1425352", "group": "7", "neighbors": ["1312277", "169797", "1770468", "843401"]}, {"id": "161994", "group": "12", "neighbors": []}, {"id": "169797", "group": "7", "neighbors": []}, {"id": "20967", "group": "7", "neighbors": []}, {"id": "210814", "group": "7", "neighbors": []}, {"id": "567841", "group": "7", "neighbors": ["1079396", "1312277", "1524498", "169797", "20967", "295863", "952821"]}, {"id": "609256", "group": "7", "neighbors": []}, {"id": "211950", "group": "7", "neighbors": ["1079396", "1143639", "1312277", "1425352", "1524498", "169797", "1770468", "20967", "210814", "266349", "295863", "567841", "609256", "843401", "952821"]}], "links": [{"source": 0, "target": 7, "value": 3}, {"source": 0, "target": 8, "value": 2}, {"source": 0, "target": 9, "value": 2}, {"source": 0, "target": 10, "value": 2}, {"source": 0, "target": 11, "value": 2}, {"source": 0, "target": 12, "value": 2}, {"source": 0, "target": 13, "value": 3}, {"source": 0, "target": 2, "value": 2}, {"source": 0, "target": 14, "value": 2}, {"source": 0, "target": 15, "value": 2}, {"source": 0, "target": 6, "value": 2}, {"source": 0, "target": 3, "value": 2}, {"source": 1, "target": 7, "value": 2}, {"source": 1, "target": 0, "value": 2}, {"source": 1, "target": 8, "value": 2}, {"source": 1, "target": 9, "value": 2}, {"source": 1, "target": 11, "value": 2}, {"source": 1, "target": 12, "value": 3}, {"source": 1, "target": 16, "value": 2}, {"source": 1, "target": 5, "value": 2}, {"source": 1, "target": 2, "value": 2}, {"source": 1, "target": 14, "value": 3}, {"source": 1, "target": 3, "value": 2}, {"source": 2, "target": 7, "value": 4}, {"source": 2, "target": 0, "value": 4}, {"source": 2, "target": 8, "value": 3}, {"source": 2, "target": 9, "value": 4}, {"source": 2, "target": 1, "value": 3}, {"source": 2, "target": 11, "value": 4}, {"source": 2, "target": 4, "value": 4}, {"source": 2, "target": 12, "value": 4}, {"source": 2, "target": 13, "value": 4}, {"source": 2, "target": 16, "value": 3}, {"source": 2, "target": 5, "value": 3}, {"source": 2, "target": 14, "value": 6}, {"source": 2, "target": 15, "value": 4}, {"source": 2, "target": 6, "value": 4}, {"source": 2, "target": 3, "value": 4}, {"source": 3, "target": 7, "value": 2}, {"source": 3, "target": 0, "value": 2}, {"source": 3, "target": 9, "value": 3}, {"source": 3, "target": 1, "value": 2}, {"source": 3, "target": 11, "value": 2}, {"source": 3, "target": 12, "value": 2}, {"source": 3, "target": 13, "value": 2}, {"source": 3, "target": 2, "value": 2}, {"source": 3, "target": 14, "value": 2}, {"source": 3, "target": 15, "value": 2}, {"source": 3, "target": 6, "value": 3}, {"source": 4, "target": 0, "value": 2}, {"source": 4, "target": 8, "value": 2}, {"source": 4, "target": 9, "value": 2}, {"source": 4, "target": 1, "value": 2}, {"source": 4, "target": 11, "value": 2}, {"source": 4, "target": 12, "value": 2}, {"source": 4, "target": 13, "value": 2}, {"source": 4, "target": 16, "value": 2}, {"source": 4, "target": 5, "value": 2}, {"source": 4, "target": 2, "value": 2}, {"source": 4, "target": 14, "value": 2}, {"source": 4, "target": 15, "value": 2}, {"source": 4, "target": 6, "value": 2}, {"source": 4, "target": 3, "value": 2}, {"source": 5, "target": 0, "value": 2}, {"source": 6, "target": 7, "value": 2}, {"source": 6, "target": 0, "value": 2}, {"source": 6, "target": 8, "value": 2}, {"source": 6, "target": 9, "value": 2}, {"source": 6, "target": 1, "value": 2}, {"source": 6, "target": 11, "value": 2}, {"source": 6, "target": 4, "value": 2}, {"source": 6, "target": 12, "value": 2}, {"source": 6, "target": 13, "value": 2}, {"source": 6, "target": 16, "value": 2}, {"source": 6, "target": 5, "value": 2}, {"source": 6, "target": 2, "value": 2}, {"source": 6, "target": 14, "value": 2}, {"source": 6, "target": 15, "value": 2}, {"source": 6, "target": 3, "value": 2}, {"source": 7, "target": 4, "value": 2}, {"source": 7, "target": 2, "value": 2}, {"source": 8, "target": 4, "value": 2}, {"source": 9, "target": 8, "value": 2}, {"source": 9, "target": 11, "value": 2}, {"source": 9, "target": 4, "value": 2}, {"source": 9, "target": 6, "value": 2}, {"source": 14, "target": 7, "value": 2}, {"source": 14, "target": 8, "value": 2}, {"source": 14, "target": 1, "value": 2}, {"source": 14, "target": 11, "value": 2}, {"source": 14, "target": 12, "value": 2}, {"source": 14, "target": 2, "value": 2}, {"source": 14, "target": 3, "value": 2}, {"source": 16, "target": 7, "value": 3}, {"source": 16, "target": 0, "value": 3}, {"source": 16, "target": 8, "value": 3}, {"source": 16, "target": 9, "value": 3}, {"source": 16, "target": 1, "value": 3}, {"source": 16, "target": 11, "value": 4}, {"source": 16, "target": 4, "value": 4}, {"source": 16, "target": 12, "value": 3}, {"source": 16, "target": 13, "value": 3}, {"source": 16, "target": 5, "value": 3}, {"source": 16, "target": 2, "value": 3}, {"source": 16, "target": 14, "value": 3}, {"source": 16, "target": 15, "value": 3}, {"source": 16, "target": 6, "value": 3}, {"source": 16, "target": 3, "value": 3}]}