{"nodes": [{"id": "839736", "neighbors": ["1002597", "1188959", "1196253", "1263311", "1295158", "133312", "1388162", "1757507", "180661", "1826870", "1874534", "1905468", "1954532", "2066972", "2080257", "291785", "379254", "480467", "532442", "580635", "638913", "646993", "684239", "821251", "829110"]}, {"id": "1001533", "neighbors": []}, {"id": "1000708", "neighbors": []}, {"id": "1002597", "neighbors": ["839736"]}, {"id": "10089", "neighbors": []}, {"id": "1011112", "neighbors": []}, {"id": "1016471", "neighbors": []}, {"id": "1022384", "neighbors": []}, {"id": "1025781", "neighbors": []}, {"id": "1028085", "neighbors": []}, {"id": "1029556", "neighbors": []}, {"id": "1029726", "neighbors": []}, {"id": "1045980", "neighbors": ["1002597", "1176992", "1643468", "256620", "384298", "688673"]}, {"id": "1049061", "neighbors": []}, {"id": "1050928", "neighbors": []}, {"id": "1058885", "neighbors": []}, {"id": "1060589", "neighbors": []}, {"id": "1067956", "neighbors": []}, {"id": "1070212", "neighbors": ["291785"]}, {"id": "1075202", "neighbors": []}, {"id": "1083363", "neighbors": []}, {"id": "1086053", "neighbors": []}, {"id": "109455", "neighbors": []}, {"id": "110075", "neighbors": []}, {"id": "1107890", "neighbors": []}, {"id": "1115919", "neighbors": []}, {"id": "1116329", "neighbors": ["1280922", "1357973", "1611783", "1627198", "179142", "1897980", "289181", "345618", "580785"]}, {"id": "1117699", "neighbors": ["380279"]}, {"id": "1119534", "neighbors": []}, {"id": "1122884", "neighbors": []}, {"id": "1128427", "neighbors": []}, {"id": "11311", "neighbors": []}, {"id": "1136377", "neighbors": []}, {"id": "1158920", "neighbors": []}, {"id": "1174742", "neighbors": []}, {"id": "1176992", "neighbors": ["1045980", "256620"]}, {"id": "1178195", "neighbors": ["1346967", "1405426", "1683303", "1858381", "1873607", "2060106", "2081131", "511781", "589598", "813636"]}, {"id": "1178625", "neighbors": []}, {"id": "1180958", "neighbors": ["1521668", "2079003", "238547"]}, {"id": "1184365", "neighbors": []}, {"id": "1188959", "neighbors": ["839736"]}, {"id": "1191555", "neighbors": []}, {"id": "1194287", "neighbors": []}, {"id": "1194932", "neighbors": []}, {"id": "1196253", "neighbors": []}, {"id": "1199860", "neighbors": []}, {"id": "120607", "neighbors": []}, {"id": "1207988", "neighbors": []}, {"id": "1213994", "neighbors": []}, {"id": "1217734", "neighbors": []}, {"id": "1219503", "neighbors": []}, {"id": "1236441", "neighbors": []}, {"id": "1246313", "neighbors": []}, {"id": "1246650", "neighbors": []}, {"id": "1246785", "neighbors": []}, {"id": "1263311", "neighbors": ["1297648", "1607944", "467299", "549003", "839736", "864019"]}, {"id": "1269351", "neighbors": ["1194287", "1366970", "1452405", "1651940", "169797", "20967", "753509", "952821"]}, {"id": "1272536", "neighbors": []}, {"id": "127426", "neighbors": []}, {"id": "1275173", "neighbors": []}, {"id": "1280922", "neighbors": ["580785"]}, {"id": "1286459", "neighbors": []}, {"id": "1295158", "neighbors": ["313274", "839736"]}, {"id": "1297648", "neighbors": []}, {"id": "1309481", "neighbors": []}, {"id": "1310270", "neighbors": []}, {"id": "1317012", "neighbors": []}, {"id": "1320383", "neighbors": []}, {"id": "1320651", "neighbors": []}, {"id": "132087", "neighbors": ["1700834"]}, {"id": "1326471", "neighbors": []}, {"id": "133312", "neighbors": ["839736"]}, {"id": "1339498", "neighbors": []}, {"id": "1344899", "neighbors": []}, {"id": "134576", "neighbors": []}, {"id": "1346096", "neighbors": []}, {"id": "1346967", "neighbors": ["1683303", "1858381", "1873607", "2060106", "2081131", "511781", "923924"]}, {"id": "1350922", "neighbors": []}, {"id": "1357973", "neighbors": ["345618", "580785"]}, {"id": "1365332", "neighbors": []}, {"id": "1366676", "neighbors": ["1372177", "1755533", "184869", "1885677", "215916", "255983", "313274", "449158", "543168", "699874", "811548", "923924"]}, {"id": "1366970", "neighbors": ["1651940", "169797", "462663", "580486", "72120", "753509"]}, {"id": "1372177", "neighbors": ["1346967", "1366676", "1755533", "184869", "1885677", "215916", "255983", "313274", "449158", "500451", "543168", "699874", "811548", "923924"]}, {"id": "138464", "neighbors": []}, {"id": "1388162", "neighbors": ["839736"]}, {"id": "1389673", "neighbors": []}, {"id": "1392457", "neighbors": []}, {"id": "1396757", "neighbors": ["1695419", "1823484", "72120", "734861"]}, {"id": "1401329", "neighbors": []}, {"id": "1405426", "neighbors": ["1178195", "1346967", "1683303", "1858381", "1873607", "2060106", "2081131", "511781", "589598", "813636"]}, {"id": "1409736", "neighbors": []}, {"id": "1414051", "neighbors": []}, {"id": "1425352", "neighbors": []}, {"id": "1425469", "neighbors": []}, {"id": "1445238", "neighbors": []}, {"id": "1448061", "neighbors": []}, {"id": "1452405", "neighbors": []}, {"id": "1452626", "neighbors": []}, {"id": "1454086", "neighbors": []}, {"id": "1455142", "neighbors": []}, {"id": "1456874", "neighbors": []}, {"id": "146240", "neighbors": ["1612579", "1687983"]}, {"id": "1470439", "neighbors": []}, {"id": "1475524", "neighbors": []}, {"id": "1481209", "neighbors": ["1029726", "1050928", "1485450", "1695419", "235093", "266280", "889291", "992688"]}, {"id": "1485450", "neighbors": []}, {"id": "148882", "neighbors": ["1695419"]}, {"id": "1491664", "neighbors": []}, {"id": "149913", "neighbors": []}, {"id": "1501359", "neighbors": []}, {"id": "1517929", "neighbors": []}, {"id": "1518969", "neighbors": ["1912459"]}, {"id": "1520446", "neighbors": []}, {"id": "1521668", "neighbors": ["856573"]}, {"id": "1525028", "neighbors": []}, {"id": "1525975", "neighbors": []}, {"id": "1539142", "neighbors": []}, {"id": "154530", "neighbors": []}, {"id": "1549032", "neighbors": []}, {"id": "1551364", "neighbors": []}, {"id": "1552214", "neighbors": []}, {"id": "1562922", "neighbors": []}, {"id": "1574967", "neighbors": []}, {"id": "1576297", "neighbors": []}, {"id": "1578455", "neighbors": []}, {"id": "1597848", "neighbors": []}, {"id": "1598265", "neighbors": []}, {"id": "160360", "neighbors": []}, {"id": "1607944", "neighbors": ["1574967", "704362", "952821"]}, {"id": "1611783", "neighbors": []}, {"id": "1612579", "neighbors": []}, {"id": "1612584", "neighbors": []}, {"id": "1616474", "neighbors": ["1627198"]}, {"id": "1616612", "neighbors": ["1825492"]}, {"id": "1625046", "neighbors": []}, {"id": "1627198", "neighbors": ["1611783", "1616474", "258503"]}, {"id": "1638566", "neighbors": []}, {"id": "1643468", "neighbors": []}, {"id": "1651940", "neighbors": ["1049061", "1194287", "1269351", "1366970", "1425352", "1452405", "169797", "20967", "580486", "753509", "888093", "952821"]}, {"id": "1658699", "neighbors": ["1713404"]}, {"id": "1661506", "neighbors": []}, {"id": "1667325", "neighbors": []}, {"id": "1675069", "neighbors": ["1661506"]}, {"id": "1675667", "neighbors": []}, {"id": "1678204", "neighbors": []}, {"id": "1679652", "neighbors": []}, {"id": "1682503", "neighbors": ["1396757", "1491664", "1947928", "1991168", "716681", "72120", "734861"]}, {"id": "1683303", "neighbors": []}, {"id": "1687029", "neighbors": []}, {"id": "1687983", "neighbors": ["146240", "1612579"]}, {"id": "1688081", "neighbors": []}, {"id": "1695419", "neighbors": ["1029726", "1050928", "1481209", "1485450", "148882", "235093", "266280", "889291", "992688"]}, {"id": "169687", "neighbors": []}, {"id": "169797", "neighbors": ["1049061", "1194287", "1269351", "1366970", "1425352", "1452405", "1651940", "1750125", "2017643", "20967", "500451", "580486", "753509", "888093", "952821"]}, {"id": "1699336", "neighbors": []}, {"id": "1700834", "neighbors": []}, {"id": "1713404", "neighbors": []}, {"id": "1721166", "neighbors": []}, {"id": "1727327", "neighbors": []}, {"id": "1730482", "neighbors": ["647751"]}, {"id": "1739976", "neighbors": []}, {"id": "1741651", "neighbors": []}, {"id": "1743546", "neighbors": []}, {"id": "1744199", "neighbors": []}, {"id": "1750125", "neighbors": []}, {"id": "1751308", "neighbors": []}, {"id": "1753118", "neighbors": []}, {"id": "1755533", "neighbors": ["1366676", "1372177", "184869"]}, {"id": "1757507", "neighbors": ["839736"]}, {"id": "1764153", "neighbors": []}, {"id": "1766671", "neighbors": ["1819320"]}, {"id": "1770586", "neighbors": ["1699336"]}, {"id": "1771245", "neighbors": []}, {"id": "1784467", "neighbors": []}, {"id": "179142", "neighbors": []}, {"id": "1803086", "neighbors": []}, {"id": "1806328", "neighbors": []}, {"id": "180661", "neighbors": ["839736"]}, {"id": "1809394", "neighbors": []}, {"id": "1817739", "neighbors": []}, {"id": "1819320", "neighbors": ["1766671"]}, {"id": "1821472", "neighbors": []}, {"id": "1823484", "neighbors": ["711179"]}, {"id": "1825492", "neighbors": ["1616612"]}, {"id": "1826870", "neighbors": ["839736"]}, {"id": "1827053", "neighbors": []}, {"id": "1831128", "neighbors": []}, {"id": "1834564", "neighbors": []}, {"id": "1835505", "neighbors": []}, {"id": "184869", "neighbors": []}, {"id": "1858381", "neighbors": ["1002597", "1178195", "1346967", "1405426", "1574967", "1683303", "1873607", "2060106", "2079003", "2081131", "467299", "511781", "589598", "813636"]}, {"id": "186115", "neighbors": []}, {"id": "1866264", "neighbors": []}, {"id": "186682", "neighbors": ["1821472", "829110", "996268"]}, {"id": "186726", "neighbors": []}, {"id": "1874534", "neighbors": ["839736"]}, {"id": "1877708", "neighbors": []}, {"id": "1878167", "neighbors": []}, {"id": "1882651", "neighbors": []}, {"id": "1883384", "neighbors": []}, {"id": "1885677", "neighbors": ["1366676", "1372177", "1755533", "184869", "215916", "255983", "313274", "449158", "543168", "699874", "811548", "923924"]}, {"id": "1894702", "neighbors": ["1998032"]}, {"id": "1897980", "neighbors": ["258503", "432283"]}, {"id": "1899557", "neighbors": []}, {"id": "1901189", "neighbors": []}, {"id": "1901680", "neighbors": []}, {"id": "1905468", "neighbors": ["839736"]}, {"id": "1910777", "neighbors": []}, {"id": "1912459", "neighbors": ["1518969"]}, {"id": "1931368", "neighbors": []}, {"id": "193689", "neighbors": []}, {"id": "1939292", "neighbors": []}, {"id": "1943228", "neighbors": ["109455", "1521668", "1525975", "1817739", "644063"]}, {"id": "1945467", "neighbors": []}, {"id": "1947928", "neighbors": ["1682503", "1835505"]}, {"id": "1954532", "neighbors": ["839736"]}, {"id": "196239", "neighbors": ["480467"]}, {"id": "197811", "neighbors": []}, {"id": "1979024", "neighbors": ["1246650", "575771"]}, {"id": "1991168", "neighbors": []}, {"id": "1994529", "neighbors": []}, {"id": "1997596", "neighbors": []}, {"id": "1998032", "neighbors": []}, {"id": "2004816", "neighbors": ["1219503", "216057"]}, {"id": "2007515", "neighbors": []}, {"id": "2007598", "neighbors": []}, {"id": "2017643", "neighbors": []}, {"id": "2025656", "neighbors": []}, {"id": "2035400", "neighbors": []}, {"id": "2060106", "neighbors": ["1346967"]}, {"id": "2066972", "neighbors": ["839736"]}, {"id": "207136", "neighbors": []}, {"id": "2078034", "neighbors": ["1744199"]}, {"id": "2079003", "neighbors": ["1180958", "1317012", "238547", "258503"]}, {"id": "2080257", "neighbors": ["839736"]}, {"id": "2081131", "neighbors": []}, {"id": "2091832", "neighbors": ["1346096"]}, {"id": "20967", "neighbors": ["1049061", "1194287", "1269351", "1366970", "1425352", "1452405", "1456874", "1651940", "169797", "580486", "753509", "888093", "952821"]}, {"id": "213290", "neighbors": []}, {"id": "214139", "neighbors": []}, {"id": "215593", "neighbors": []}, {"id": "215916", "neighbors": ["1366676", "1372177", "1755533", "184869", "1885677", "255983", "313274", "449158", "543168", "699874", "811548", "923924"]}, {"id": "216057", "neighbors": []}, {"id": "225622", "neighbors": []}, {"id": "227048", "neighbors": ["1396757", "1491664", "1682503", "1991168", "716681", "72120", "734861"]}, {"id": "233486", "neighbors": []}, {"id": "235093", "neighbors": ["1029726", "1050928", "1481209", "1485450", "1695419", "266280", "889291", "992688"]}, {"id": "238547", "neighbors": ["1180958", "1194287", "1317012", "1485450", "2079003", "258503"]}, {"id": "239133", "neighbors": []}, {"id": "241275", "neighbors": []}, {"id": "255983", "neighbors": ["1366676"]}, {"id": "256620", "neighbors": []}, {"id": "258503", "neighbors": ["238547"]}, {"id": "263633", "neighbors": []}, {"id": "266280", "neighbors": ["1029726", "1050928", "1481209", "1485450", "1695419", "235093", "889291", "992688", "999107"]}, {"id": "274315", "neighbors": []}, {"id": "279576", "neighbors": []}, {"id": "289181", "neighbors": ["1116329", "1897980"]}, {"id": "291785", "neighbors": ["839736"]}, {"id": "298495", "neighbors": []}, {"id": "304586", "neighbors": []}, {"id": "313274", "neighbors": ["1295158", "1366676"]}, {"id": "331284", "neighbors": []}, {"id": "33357", "neighbors": []}, {"id": "336328", "neighbors": []}, {"id": "345618", "neighbors": ["1357973"]}, {"id": "352434", "neighbors": []}, {"id": "353069", "neighbors": []}, {"id": "359592", "neighbors": []}, {"id": "36486", "neighbors": ["1246313", "1388162", "1899557", "291785", "500215", "731443"]}, {"id": "366288", "neighbors": []}, {"id": "379254", "neighbors": ["462663", "821251", "839736"]}, {"id": "380279", "neighbors": ["1199860", "127426"]}, {"id": "382206", "neighbors": []}, {"id": "383251", "neighbors": []}, {"id": "384298", "neighbors": []}, {"id": "394459", "neighbors": []}, {"id": "398292", "neighbors": []}, {"id": "408012", "neighbors": []}, {"id": "409939", "neighbors": ["937230"]}, {"id": "414676", "neighbors": []}, {"id": "420615", "neighbors": []}, {"id": "423861", "neighbors": []}, {"id": "427660", "neighbors": []}, {"id": "432283", "neighbors": ["289181"]}, {"id": "439105", "neighbors": ["580064"]}, {"id": "449158", "neighbors": ["1366676", "1372177", "1755533", "184869", "1885677", "215916", "255983", "313274", "543168", "699874", "811548", "923924"]}, {"id": "450819", "neighbors": []}, {"id": "462663", "neighbors": ["379254"]}, {"id": "467299", "neighbors": []}, {"id": "469296", "neighbors": []}, {"id": "473436", "neighbors": []}, {"id": "480467", "neighbors": ["196239", "839736"]}, {"id": "4908", "neighbors": []}, {"id": "498009", "neighbors": []}, {"id": "500215", "neighbors": ["1346967", "543168"]}, {"id": "500451", "neighbors": []}, {"id": "504304", "neighbors": []}, {"id": "511781", "neighbors": ["1178195", "1405426", "1683303", "1858381", "1873607", "2060106", "2081131", "589598"]}, {"id": "527693", "neighbors": []}, {"id": "532442", "neighbors": ["839736"]}, {"id": "533015", "neighbors": []}, {"id": "535082", "neighbors": []}, {"id": "538711", "neighbors": []}, {"id": "538957", "neighbors": []}, {"id": "543168", "neighbors": ["1366676", "1372177", "1755533", "184869", "1885677", "215916", "255983", "313274", "449158", "699874", "811548", "923924"]}, {"id": "557868", "neighbors": []}, {"id": "56467", "neighbors": ["770252"]}, {"id": "574210", "neighbors": ["149913"]}, {"id": "575771", "neighbors": ["1246650"]}, {"id": "579220", "neighbors": []}, {"id": "580064", "neighbors": ["439105"]}, {"id": "580486", "neighbors": ["753509"]}, {"id": "580635", "neighbors": []}, {"id": "580785", "neighbors": []}, {"id": "589598", "neighbors": ["511781"]}, {"id": "616205", "neighbors": []}, {"id": "637839", "neighbors": []}, {"id": "638913", "neighbors": ["839736"]}, {"id": "639466", "neighbors": []}, {"id": "643447", "neighbors": []}, {"id": "644063", "neighbors": ["109455", "1525975", "1817739", "1943228"]}, {"id": "646215", "neighbors": []}, {"id": "646993", "neighbors": ["839736"]}, {"id": "647751", "neighbors": []}, {"id": "658416", "neighbors": []}, {"id": "662174", "neighbors": []}, {"id": "67063", "neighbors": []}, {"id": "674787", "neighbors": []}, {"id": "675561", "neighbors": []}, {"id": "684239", "neighbors": ["839736"]}, {"id": "688673", "neighbors": []}, {"id": "692898", "neighbors": []}, {"id": "697944", "neighbors": []}, {"id": "699874", "neighbors": []}, {"id": "704004", "neighbors": []}, {"id": "704362", "neighbors": []}, {"id": "707627", "neighbors": []}, {"id": "709279", "neighbors": []}, {"id": "711179", "neighbors": ["1823484"]}, {"id": "711301", "neighbors": ["1611783"]}, {"id": "716681", "neighbors": []}, {"id": "72120", "neighbors": ["1396757", "1695419", "1823484", "734861"]}, {"id": "730971", "neighbors": []}, {"id": "731443", "neighbors": ["1246313", "1388162", "1899557", "291785", "36486", "500215"]}, {"id": "734861", "neighbors": []}, {"id": "736288", "neighbors": []}, {"id": "736972", "neighbors": []}, {"id": "73832", "neighbors": []}, {"id": "739695", "neighbors": ["467299", "549003"]}, {"id": "743963", "neighbors": ["1070212", "1158920", "1317012", "1576297", "1753118", "239133", "398292"]}, {"id": "744631", "neighbors": []}, {"id": "750163", "neighbors": []}, {"id": "753509", "neighbors": ["1049061", "1194287", "1269351", "1366970", "1425352", "1452405", "1651940", "169797", "20967", "580486", "888093", "952821"]}, {"id": "755822", "neighbors": []}, {"id": "766528", "neighbors": []}, {"id": "770252", "neighbors": []}, {"id": "776705", "neighbors": []}, {"id": "777006", "neighbors": []}, {"id": "77892", "neighbors": []}, {"id": "786425", "neighbors": []}, {"id": "788040", "neighbors": []}, {"id": "811548", "neighbors": ["923924"]}, {"id": "811616", "neighbors": []}, {"id": "8129", "neighbors": []}, {"id": "81292", "neighbors": []}, {"id": "813636", "neighbors": ["2060106"]}, {"id": "816938", "neighbors": []}, {"id": "821251", "neighbors": ["379254", "462663", "839736"]}, {"id": "821572", "neighbors": []}, {"id": "822936", "neighbors": []}, {"id": "827020", "neighbors": []}, {"id": "829110", "neighbors": ["839736"]}, {"id": "854341", "neighbors": []}, {"id": "856573", "neighbors": ["1521668", "1835505"]}, {"id": "874070", "neighbors": []}, {"id": "880619", "neighbors": []}, {"id": "888093", "neighbors": ["1049061", "1194287", "1269351", "1366970", "1425352", "1452405", "1651940", "169797", "20967", "580486", "753509", "952821"]}, {"id": "889291", "neighbors": []}, {"id": "892885", "neighbors": []}, {"id": "903769", "neighbors": []}, {"id": "914446", "neighbors": []}, {"id": "923924", "neighbors": ["1366676", "1885677", "215916", "255983", "313274", "449158", "543168", "699874", "811548"]}, {"id": "925094", "neighbors": ["839736"]}, {"id": "937230", "neighbors": ["409939"]}, {"id": "939665", "neighbors": []}, {"id": "94067", "neighbors": []}, {"id": "941089", "neighbors": []}, {"id": "942846", "neighbors": []}, {"id": "952821", "neighbors": ["169797"]}, {"id": "969502", "neighbors": []}, {"id": "985107", "neighbors": ["462663", "942846"]}, {"id": "989161", "neighbors": []}, {"id": "990811", "neighbors": []}, {"id": "992688", "neighbors": ["1029726", "1050928", "1481209", "1485450", "1695419", "235093", "266280", "889291"]}, {"id": "996258", "neighbors": []}, {"id": "996268", "neighbors": []}, {"id": "998575", "neighbors": []}, {"id": "999107", "neighbors": ["263633"]}, {"id": "1492679", "neighbors": []}, {"id": "549003", "neighbors": []}, {"id": "864019", "neighbors": []}, {"id": "1873607", "neighbors": []}, {"id": "1367089", "neighbors": []}, {"id": "183920", "neighbors": []}], "links": [{"source": 0, "target": 3, "value": 2}, {"source": 0, "target": 40, "value": 2}, {"source": 0, "target": 44, "value": 2}, {"source": 0, "target": 55, "value": 2}, {"source": 0, "target": 62, "value": 2}, {"source": 0, "target": 71, "value": 2}, {"source": 0, "target": 84, "value": 2}, {"source": 0, "target": 168, "value": 2}, {"source": 0, "target": 177, "value": 2}, {"source": 0, "target": 184, "value": 2}, {"source": 0, "target": 195, "value": 2}, {"source": 0, "target": 206, "value": 2}, {"source": 0, "target": 215, "value": 2}, {"source": 0, "target": 230, "value": 2}, {"source": 0, "target": 234, "value": 2}, {"source": 0, "target": 258, "value": 2}, {"source": 0, "target": 271, "value": 2}, {"source": 0, "target": 292, "value": 2}, {"source": 0, "target": 300, "value": 2}, {"source": 0, "target": 313, "value": 2}, {"source": 0, "target": 318, "value": 2}, {"source": 0, "target": 323, "value": 2}, {"source": 0, "target": 330, "value": 2}, {"source": 0, "target": 368, "value": 2}, {"source": 0, "target": 372, "value": 2}, {"source": 3, "target": 0, "value": 2}, {"source": 12, "target": 3, "value": 3}, {"source": 12, "target": 35, "value": 3}, {"source": 12, "target": 137, "value": 3}, {"source": 12, "target": 251, "value": 3}, {"source": 12, "target": 275, "value": 3}, {"source": 12, "target": 331, "value": 3}, {"source": 18, "target": 258, "value": 2}, {"source": 26, "target": 60, "value": 2}, {"source": 26, "target": 78, "value": 2}, {"source": 26, "target": 129, "value": 3}, {"source": 26, "target": 135, "value": 3}, {"source": 26, "target": 174, "value": 2}, {"source": 26, "target": 202, "value": 2}, {"source": 26, "target": 257, "value": 3}, {"source": 26, "target": 265, "value": 2}, {"source": 26, "target": 314, "value": 2}, {"source": 27, "target": 272, "value": 2}, {"source": 35, "target": 12, "value": 2}, {"source": 35, "target": 251, "value": 2}, {"source": 36, "target": 76, "value": 2}, {"source": 36, "target": 89, "value": 4}, {"source": 36, "target": 147, "value": 2}, {"source": 36, "target": 190, "value": 3}, {"source": 36, "target": 402, "value": 3}, {"source": 36, "target": 229, "value": 3}, {"source": 36, "target": 235, "value": 2}, {"source": 36, "target": 298, "value": 3}, {"source": 36, "target": 315, "value": 3}, {"source": 36, "target": 366, "value": 2}, {"source": 38, "target": 113, "value": 2}, {"source": 38, "target": 233, "value": 3}, {"source": 38, "target": 247, "value": 3}, {"source": 40, "target": 0, "value": 2}, {"source": 55, "target": 63, "value": 2}, {"source": 55, "target": 128, "value": 2}, {"source": 55, "target": 289, "value": 2}, {"source": 55, "target": 400, "value": 2}, {"source": 55, "target": 0, "value": 2}, {"source": 55, "target": 401, "value": 2}, {"source": 56, "target": 42, "value": 2}, {"source": 56, "target": 81, "value": 2}, {"source": 56, "target": 96, "value": 2}, {"source": 56, "target": 138, "value": 2}, {"source": 56, "target": 153, "value": 2}, {"source": 56, "target": 237, "value": 2}, {"source": 56, "target": 353, "value": 3}, {"source": 56, "target": 389, "value": 2}, {"source": 60, "target": 314, "value": 2}, {"source": 62, "target": 261, "value": 2}, {"source": 62, "target": 0, "value": 2}, {"source": 69, "target": 155, "value": 2}, {"source": 71, "target": 0, "value": 2}, {"source": 76, "target": 147, "value": 2}, {"source": 76, "target": 190, "value": 2}, {"source": 76, "target": 402, "value": 2}, {"source": 76, "target": 229, "value": 2}, {"source": 76, "target": 235, "value": 2}, {"source": 76, "target": 298, "value": 2}, {"source": 76, "target": 382, "value": 2}, {"source": 78, "target": 265, "value": 3}, {"source": 78, "target": 314, "value": 2}, {"source": 80, "target": 82, "value": 4}, {"source": 80, "target": 167, "value": 5}, {"source": 80, "target": 189, "value": 5}, {"source": 80, "target": 200, "value": 6}, {"source": 80, "target": 241, "value": 5}, {"source": 80, "target": 250, "value": 4}, {"source": 80, "target": 261, "value": 5}, {"source": 80, "target": 286, "value": 5}, {"source": 80, "target": 305, "value": 5}, {"source": 80, "target": 334, "value": 5}, {"source": 80, "target": 362, "value": 5}, {"source": 80, "target": 382, "value": 5}, {"source": 81, "target": 138, "value": 2}, {"source": 81, "target": 153, "value": 2}, {"source": 81, "target": 288, "value": 2}, {"source": 81, "target": 312, "value": 3}, {"source": 81, "target": 342, "value": 2}, {"source": 81, "target": 353, "value": 2}, {"source": 82, "target": 76, "value": 3}, {"source": 82, "target": 80, "value": 3}, {"source": 82, "target": 167, "value": 4}, {"source": 82, "target": 189, "value": 3}, {"source": 82, "target": 200, "value": 3}, {"source": 82, "target": 241, "value": 3}, {"source": 82, "target": 250, "value": 3}, {"source": 82, "target": 261, "value": 4}, {"source": 82, "target": 286, "value": 3}, {"source": 82, "target": 296, "value": 2}, {"source": 82, "target": 305, "value": 3}, {"source": 82, "target": 334, "value": 3}, {"source": 82, "target": 362, "value": 3}, {"source": 82, "target": 382, "value": 3}, {"source": 84, "target": 0, "value": 2}, {"source": 87, "target": 151, "value": 2}, {"source": 87, "target": 182, "value": 2}, {"source": 87, "target": 342, "value": 3}, {"source": 87, "target": 345, "value": 3}, {"source": 89, "target": 36, "value": 3}, {"source": 89, "target": 76, "value": 2}, {"source": 89, "target": 147, "value": 3}, {"source": 89, "target": 190, "value": 3}, {"source": 89, "target": 402, "value": 3}, {"source": 89, "target": 229, "value": 3}, {"source": 89, "target": 235, "value": 3}, {"source": 89, "target": 298, "value": 3}, {"source": 89, "target": 315, "value": 3}, {"source": 89, "target": 366, "value": 2}, {"source": 101, "target": 130, "value": 3}, {"source": 101, "target": 149, "value": 4}, {"source": 104, "target": 11, "value": 3}, {"source": 104, "target": 14, "value": 3}, {"source": 104, "target": 105, "value": 3}, {"source": 104, "target": 151, "value": 3}, {"source": 104, "target": 246, "value": 4}, {"source": 104, "target": 254, "value": 3}, {"source": 104, "target": 378, "value": 3}, {"source": 104, "target": 394, "value": 3}, {"source": 106, "target": 151, "value": 5}, {"source": 111, "target": 208, "value": 2}, {"source": 113, "target": 374, "value": 2}, {"source": 128, "target": 122, "value": 2}, {"source": 128, "target": 336, "value": 2}, {"source": 128, "target": 389, "value": 2}, {"source": 132, "target": 135, "value": 6}, {"source": 133, "target": 183, "value": 4}, {"source": 135, "target": 129, "value": 2}, {"source": 135, "target": 132, "value": 4}, {"source": 135, "target": 252, "value": 3}, {"source": 138, "target": 13, "value": 4}, {"source": 138, "target": 42, "value": 4}, {"source": 138, "target": 56, "value": 4}, {"source": 138, "target": 81, "value": 5}, {"source": 138, "target": 92, "value": 4}, {"source": 138, "target": 96, "value": 4}, {"source": 138, "target": 153, "value": 5}, {"source": 138, "target": 237, "value": 7}, {"source": 138, "target": 312, "value": 5}, {"source": 138, "target": 353, "value": 4}, {"source": 138, "target": 377, "value": 4}, {"source": 138, "target": 389, "value": 4}, {"source": 139, "target": 156, "value": 3}, {"source": 142, "target": 140, "value": 2}, {"source": 146, "target": 87, "value": 3}, {"source": 146, "target": 107, "value": 2}, {"source": 146, "target": 214, "value": 2}, {"source": 146, "target": 219, "value": 3}, {"source": 146, "target": 341, "value": 2}, {"source": 146, "target": 342, "value": 2}, {"source": 146, "target": 345, "value": 2}, {"source": 149, "target": 101, "value": 4}, {"source": 149, "target": 130, "value": 4}, {"source": 151, "target": 11, "value": 2}, {"source": 151, "target": 14, "value": 2}, {"source": 151, "target": 104, "value": 2}, {"source": 151, "target": 105, "value": 2}, {"source": 151, "target": 106, "value": 4}, {"source": 151, "target": 246, "value": 2}, {"source": 151, "target": 254, "value": 2}, {"source": 151, "target": 378, "value": 2}, {"source": 151, "target": 394, "value": 3}, {"source": 153, "target": 13, "value": 4}, {"source": 153, "target": 42, "value": 4}, {"source": 153, "target": 56, "value": 4}, {"source": 153, "target": 81, "value": 4}, {"source": 153, "target": 92, "value": 4}, {"source": 153, "target": 96, "value": 4}, {"source": 153, "target": 138, "value": 4}, {"source": 153, "target": 164, "value": 2}, {"source": 153, "target": 226, "value": 2}, {"source": 153, "target": 237, "value": 6}, {"source": 153, "target": 296, "value": 2}, {"source": 153, "target": 312, "value": 5}, {"source": 153, "target": 353, "value": 4}, {"source": 153, "target": 377, "value": 6}, {"source": 153, "target": 389, "value": 4}, {"source": 159, "target": 324, "value": 2}, {"source": 167, "target": 80, "value": 2}, {"source": 167, "target": 82, "value": 2}, {"source": 167, "target": 189, "value": 2}, {"source": 168, "target": 0, "value": 2}, {"source": 170, "target": 180, "value": 2}, {"source": 171, "target": 154, "value": 3}, {"source": 177, "target": 0, "value": 2}, {"source": 180, "target": 170, "value": 2}, {"source": 182, "target": 339, "value": 2}, {"source": 183, "target": 133, "value": 2}, {"source": 184, "target": 0, "value": 2}, {"source": 190, "target": 3, "value": 2}, {"source": 190, "target": 36, "value": 3}, {"source": 190, "target": 76, "value": 3}, {"source": 190, "target": 89, "value": 3}, {"source": 190, "target": 122, "value": 2}, {"source": 190, "target": 147, "value": 2}, {"source": 190, "target": 402, "value": 3}, {"source": 190, "target": 229, "value": 3}, {"source": 190, "target": 233, "value": 3}, {"source": 190, "target": 235, "value": 3}, {"source": 190, "target": 289, "value": 2}, {"source": 190, "target": 298, "value": 2}, {"source": 190, "target": 315, "value": 2}, {"source": 190, "target": 366, "value": 2}, {"source": 193, "target": 181, "value": 2}, {"source": 193, "target": 372, "value": 2}, {"source": 193, "target": 396, "value": 2}, {"source": 195, "target": 0, "value": 2}, {"source": 200, "target": 80, "value": 2}, {"source": 200, "target": 82, "value": 3}, {"source": 200, "target": 167, "value": 3}, {"source": 200, "target": 189, "value": 2}, {"source": 200, "target": 241, "value": 2}, {"source": 200, "target": 250, "value": 2}, {"source": 200, "target": 261, "value": 2}, {"source": 200, "target": 286, "value": 3}, {"source": 200, "target": 305, "value": 2}, {"source": 200, "target": 334, "value": 2}, {"source": 200, "target": 362, "value": 2}, {"source": 200, "target": 382, "value": 2}, {"source": 201, "target": 222, "value": 2}, {"source": 202, "target": 252, "value": 4}, {"source": 202, "target": 284, "value": 4}, {"source": 206, "target": 0, "value": 3}, {"source": 208, "target": 111, "value": 2}, {"source": 212, "target": 22, "value": 4}, {"source": 212, "target": 113, "value": 2}, {"source": 212, "target": 115, "value": 4}, {"source": 212, "target": 179, "value": 3}, {"source": 212, "target": 321, "value": 4}, {"source": 214, "target": 146, "value": 3}, {"source": 214, "target": 188, "value": 2}, {"source": 215, "target": 0, "value": 2}, {"source": 216, "target": 292, "value": 3}, {"source": 218, "target": 53, "value": 3}, {"source": 218, "target": 309, "value": 2}, {"source": 223, "target": 50, "value": 2}, {"source": 223, "target": 242, "value": 2}, {"source": 229, "target": 76, "value": 2}, {"source": 230, "target": 0, "value": 2}, {"source": 232, "target": 163, "value": 2}, {"source": 233, "target": 38, "value": 2}, {"source": 233, "target": 66, "value": 2}, {"source": 233, "target": 247, "value": 3}, {"source": 233, "target": 252, "value": 2}, {"source": 234, "target": 0, "value": 2}, {"source": 236, "target": 75, "value": 2}, {"source": 237, "target": 13, "value": 3}, {"source": 237, "target": 42, "value": 5}, {"source": 237, "target": 56, "value": 5}, {"source": 237, "target": 81, "value": 3}, {"source": 237, "target": 92, "value": 4}, {"source": 237, "target": 96, "value": 5}, {"source": 237, "target": 100, "value": 2}, {"source": 237, "target": 138, "value": 4}, {"source": 237, "target": 153, "value": 5}, {"source": 237, "target": 312, "value": 5}, {"source": 237, "target": 353, "value": 6}, {"source": 237, "target": 377, "value": 3}, {"source": 237, "target": 389, "value": 4}, {"source": 241, "target": 80, "value": 2}, {"source": 241, "target": 82, "value": 2}, {"source": 241, "target": 167, "value": 2}, {"source": 241, "target": 189, "value": 2}, {"source": 241, "target": 200, "value": 2}, {"source": 241, "target": 250, "value": 2}, {"source": 241, "target": 261, "value": 2}, {"source": 241, "target": 286, "value": 2}, {"source": 241, "target": 305, "value": 2}, {"source": 241, "target": 334, "value": 2}, {"source": 241, "target": 362, "value": 2}, {"source": 241, "target": 382, "value": 2}, {"source": 244, "target": 87, "value": 3}, {"source": 244, "target": 107, "value": 3}, {"source": 244, "target": 146, "value": 3}, {"source": 244, "target": 219, "value": 3}, {"source": 244, "target": 341, "value": 3}, {"source": 244, "target": 342, "value": 3}, {"source": 244, "target": 345, "value": 3}, {"source": 246, "target": 11, "value": 2}, {"source": 246, "target": 14, "value": 2}, {"source": 246, "target": 104, "value": 2}, {"source": 246, "target": 105, "value": 2}, {"source": 246, "target": 151, "value": 2}, {"source": 246, "target": 254, "value": 2}, {"source": 246, "target": 378, "value": 2}, {"source": 246, "target": 394, "value": 2}, {"source": 247, "target": 38, "value": 3}, {"source": 247, "target": 42, "value": 2}, {"source": 247, "target": 66, "value": 2}, {"source": 247, "target": 105, "value": 2}, {"source": 247, "target": 233, "value": 3}, {"source": 247, "target": 252, "value": 2}, {"source": 250, "target": 80, "value": 2}, {"source": 252, "target": 247, "value": 2}, {"source": 254, "target": 11, "value": 3}, {"source": 254, "target": 14, "value": 3}, {"source": 254, "target": 104, "value": 3}, {"source": 254, "target": 105, "value": 3}, {"source": 254, "target": 151, "value": 3}, {"source": 254, "target": 246, "value": 3}, {"source": 254, "target": 378, "value": 3}, {"source": 254, "target": 394, "value": 4}, {"source": 254, "target": 398, "value": 2}, {"source": 257, "target": 26, "value": 2}, {"source": 257, "target": 202, "value": 2}, {"source": 258, "target": 0, "value": 2}, {"source": 261, "target": 62, "value": 2}, {"source": 261, "target": 80, "value": 2}, {"source": 265, "target": 78, "value": 2}, {"source": 269, "target": 52, "value": 2}, {"source": 269, "target": 84, "value": 2}, {"source": 269, "target": 203, "value": 2}, {"source": 269, "target": 258, "value": 2}, {"source": 269, "target": 295, "value": 2}, {"source": 269, "target": 344, "value": 2}, {"source": 271, "target": 288, "value": 2}, {"source": 271, "target": 368, "value": 3}, {"source": 271, "target": 0, "value": 2}, {"source": 272, "target": 45, "value": 2}, {"source": 272, "target": 58, "value": 2}, {"source": 279, "target": 384, "value": 2}, {"source": 284, "target": 257, "value": 2}, {"source": 285, "target": 311, "value": 6}, {"source": 286, "target": 80, "value": 2}, {"source": 286, "target": 82, "value": 2}, {"source": 286, "target": 167, "value": 2}, {"source": 286, "target": 189, "value": 2}, {"source": 286, "target": 200, "value": 2}, {"source": 286, "target": 241, "value": 2}, {"source": 286, "target": 250, "value": 2}, {"source": 286, "target": 261, "value": 2}, {"source": 286, "target": 305, "value": 2}, {"source": 286, "target": 334, "value": 2}, {"source": 286, "target": 362, "value": 2}, {"source": 286, "target": 382, "value": 2}, {"source": 288, "target": 271, "value": 2}, {"source": 292, "target": 216, "value": 4}, {"source": 292, "target": 0, "value": 2}, {"source": 295, "target": 76, "value": 2}, {"source": 295, "target": 305, "value": 2}, {"source": 298, "target": 36, "value": 2}, {"source": 298, "target": 89, "value": 2}, {"source": 298, "target": 147, "value": 2}, {"source": 298, "target": 190, "value": 2}, {"source": 298, "target": 402, "value": 2}, {"source": 298, "target": 229, "value": 2}, {"source": 298, "target": 235, "value": 2}, {"source": 298, "target": 315, "value": 3}, {"source": 300, "target": 0, "value": 2}, {"source": 305, "target": 80, "value": 2}, {"source": 305, "target": 82, "value": 2}, {"source": 305, "target": 167, "value": 2}, {"source": 305, "target": 189, "value": 2}, {"source": 305, "target": 200, "value": 3}, {"source": 305, "target": 241, "value": 3}, {"source": 305, "target": 250, "value": 3}, {"source": 305, "target": 261, "value": 3}, {"source": 305, "target": 286, "value": 3}, {"source": 305, "target": 334, "value": 3}, {"source": 305, "target": 362, "value": 2}, {"source": 305, "target": 382, "value": 3}, {"source": 307, "target": 356, "value": 2}, {"source": 308, "target": 108, "value": 2}, {"source": 309, "target": 53, "value": 2}, {"source": 311, "target": 285, "value": 4}, {"source": 312, "target": 353, "value": 2}, {"source": 315, "target": 298, "value": 2}, {"source": 318, "target": 0, "value": 2}, {"source": 321, "target": 22, "value": 2}, {"source": 321, "target": 115, "value": 2}, {"source": 321, "target": 179, "value": 2}, {"source": 321, "target": 212, "value": 3}, {"source": 323, "target": 0, "value": 2}, {"source": 330, "target": 0, "value": 2}, {"source": 339, "target": 182, "value": 2}, {"source": 340, "target": 129, "value": 2}, {"source": 342, "target": 87, "value": 2}, {"source": 342, "target": 151, "value": 2}, {"source": 342, "target": 182, "value": 2}, {"source": 342, "target": 345, "value": 3}, {"source": 344, "target": 52, "value": 2}, {"source": 344, "target": 84, "value": 2}, {"source": 344, "target": 203, "value": 2}, {"source": 344, "target": 258, "value": 2}, {"source": 344, "target": 269, "value": 2}, {"source": 344, "target": 295, "value": 2}, {"source": 349, "target": 289, "value": 2}, {"source": 349, "target": 400, "value": 2}, {"source": 350, "target": 18, "value": 2}, {"source": 350, "target": 33, "value": 2}, {"source": 350, "target": 66, "value": 2}, {"source": 350, "target": 123, "value": 2}, {"source": 350, "target": 166, "value": 2}, {"source": 350, "target": 248, "value": 2}, {"source": 350, "target": 277, "value": 3}, {"source": 353, "target": 13, "value": 2}, {"source": 353, "target": 42, "value": 3}, {"source": 353, "target": 56, "value": 2}, {"source": 353, "target": 81, "value": 5}, {"source": 353, "target": 92, "value": 2}, {"source": 353, "target": 96, "value": 3}, {"source": 353, "target": 138, "value": 3}, {"source": 353, "target": 153, "value": 3}, {"source": 353, "target": 237, "value": 3}, {"source": 353, "target": 312, "value": 4}, {"source": 353, "target": 377, "value": 2}, {"source": 353, "target": 389, "value": 2}, {"source": 362, "target": 382, "value": 2}, {"source": 366, "target": 229, "value": 2}, {"source": 368, "target": 271, "value": 4}, {"source": 368, "target": 288, "value": 4}, {"source": 368, "target": 0, "value": 2}, {"source": 372, "target": 0, "value": 2}, {"source": 374, "target": 113, "value": 2}, {"source": 374, "target": 188, "value": 2}, {"source": 377, "target": 13, "value": 2}, {"source": 377, "target": 42, "value": 2}, {"source": 377, "target": 56, "value": 2}, {"source": 377, "target": 81, "value": 2}, {"source": 377, "target": 92, "value": 2}, {"source": 377, "target": 96, "value": 2}, {"source": 377, "target": 138, "value": 2}, {"source": 377, "target": 153, "value": 2}, {"source": 377, "target": 237, "value": 2}, {"source": 377, "target": 312, "value": 2}, {"source": 377, "target": 353, "value": 2}, {"source": 377, "target": 389, "value": 2}, {"source": 382, "target": 80, "value": 3}, {"source": 382, "target": 200, "value": 2}, {"source": 382, "target": 241, "value": 2}, {"source": 382, "target": 250, "value": 3}, {"source": 382, "target": 261, "value": 2}, {"source": 382, "target": 286, "value": 2}, {"source": 382, "target": 305, "value": 2}, {"source": 382, "target": 334, "value": 2}, {"source": 382, "target": 362, "value": 2}, {"source": 383, "target": 0, "value": 2}, {"source": 384, "target": 279, "value": 2}, {"source": 389, "target": 153, "value": 2}, {"source": 391, "target": 288, "value": 2}, {"source": 391, "target": 388, "value": 2}, {"source": 394, "target": 11, "value": 2}, {"source": 394, "target": 14, "value": 2}, {"source": 394, "target": 104, "value": 2}, {"source": 394, "target": 105, "value": 2}, {"source": 394, "target": 151, "value": 3}, {"source": 394, "target": 246, "value": 2}, {"source": 394, "target": 254, "value": 2}, {"source": 394, "target": 378, "value": 2}, {"source": 398, "target": 253, "value": 2}]}