{"nodes": [{"id": "1491664"}, {"id": "1176667"}, {"id": "1254510"}, {"id": "227048"}, {"id": "750980"}, {"id": "839736"}, {"id": "1289734"}, {"id": "1788018"}, {"id": "638964"}], "links": [{"source": 0, "target": 1, "value": 1}, {"source": 0, "target": 2, "value": 1}, {"source": 0, "target": 3, "value": 1}, {"source": 0, "target": 4, "value": 1}, {"source": 0, "target": 5, "value": 1}, {"source": 1, "target": 0, "value": 4}, {"source": 3, "target": 0, "value": 3}, {"source": 6, "target": 0, "value": 3}, {"source": 7, "target": 0, "value": 3}, {"source": 8, "target": 0, "value": 3}]}