{"nodes": [{"id": "317896", "neighbors": ["1450891"]}, {"id": "142693", "neighbors": ["1331174", "13357", "1348091", "1450891", "149510", "1525717", "1641935", "1670205", "1731218", "1997248", "257110", "317896", "365151", "413957", "46690", "507619", "604465", "619071", "625158", "71352", "719374", "769128", "783769", "916271", "932733"]}, {"id": "1348091", "neighbors": ["1331174", "13357", "142693", "149510", "1525717", "1641935", "1670205", "1731218", "257110", "413957", "46690", "507619", "604465", "619071", "71352", "719374", "769128", "783769"]}, {"id": "149510", "neighbors": []}, {"id": "1525717", "neighbors": []}, {"id": "1641935", "neighbors": ["46690"]}, {"id": "1670205", "neighbors": ["317896"]}, {"id": "1731218", "neighbors": ["149510"]}, {"id": "1331174", "neighbors": []}, {"id": "13357", "neighbors": []}, {"id": "1450891", "neighbors": ["149510", "1525717", "1641935", "1731218", "1997248", "365151", "507619", "625158", "719374", "783769", "916271"]}, {"id": "1997248", "neighbors": []}, {"id": "257110", "neighbors": []}, {"id": "365151", "neighbors": []}, {"id": "413957", "neighbors": []}, {"id": "46690", "neighbors": []}, {"id": "507619", "neighbors": ["1348091", "46690"]}, {"id": "604465", "neighbors": []}, {"id": "619071", "neighbors": []}, {"id": "625158", "neighbors": []}, {"id": "71352", "neighbors": []}, {"id": "719374", "neighbors": []}, {"id": "769128", "neighbors": []}, {"id": "783769", "neighbors": []}, {"id": "916271", "neighbors": []}, {"id": "external", "neighbors": []}, {"id": "932733", "neighbors": []}], "links": [{"source": 0, "target": 10, "value": 2}, {"source": 1, "target": 8, "value": 2}, {"source": 1, "target": 9, "value": 2}, {"source": 1, "target": 2, "value": 2}, {"source": 1, "target": 10, "value": 2}, {"source": 1, "target": 3, "value": 2}, {"source": 1, "target": 4, "value": 2}, {"source": 1, "target": 5, "value": 2}, {"source": 1, "target": 6, "value": 2}, {"source": 1, "target": 7, "value": 2}, {"source": 1, "target": 11, "value": 2}, {"source": 1, "target": 12, "value": 2}, {"source": 1, "target": 0, "value": 2}, {"source": 1, "target": 13, "value": 2}, {"source": 1, "target": 14, "value": 2}, {"source": 1, "target": 15, "value": 2}, {"source": 1, "target": 16, "value": 2}, {"source": 1, "target": 17, "value": 2}, {"source": 1, "target": 18, "value": 2}, {"source": 1, "target": 19, "value": 2}, {"source": 1, "target": 20, "value": 2}, {"source": 1, "target": 21, "value": 2}, {"source": 1, "target": 22, "value": 2}, {"source": 1, "target": 23, "value": 2}, {"source": 1, "target": 24, "value": 2}, {"source": 1, "target": 26, "value": 2}, {"source": 2, "target": 8, "value": 2}, {"source": 2, "target": 9, "value": 2}, {"source": 2, "target": 1, "value": 2}, {"source": 2, "target": 3, "value": 2}, {"source": 2, "target": 4, "value": 2}, {"source": 2, "target": 5, "value": 2}, {"source": 2, "target": 6, "value": 2}, {"source": 2, "target": 7, "value": 2}, {"source": 2, "target": 12, "value": 2}, {"source": 2, "target": 14, "value": 2}, {"source": 2, "target": 15, "value": 2}, {"source": 2, "target": 16, "value": 2}, {"source": 2, "target": 17, "value": 2}, {"source": 2, "target": 18, "value": 2}, {"source": 2, "target": 20, "value": 2}, {"source": 2, "target": 21, "value": 2}, {"source": 2, "target": 22, "value": 2}, {"source": 2, "target": 23, "value": 2}, {"source": 5, "target": 15, "value": 2}, {"source": 6, "target": 0, "value": 2}, {"source": 7, "target": 3, "value": 2}, {"source": 10, "target": 3, "value": 2}, {"source": 10, "target": 4, "value": 2}, {"source": 10, "target": 5, "value": 2}, {"source": 10, "target": 7, "value": 2}, {"source": 10, "target": 11, "value": 2}, {"source": 10, "target": 13, "value": 2}, {"source": 10, "target": 16, "value": 2}, {"source": 10, "target": 19, "value": 2}, {"source": 10, "target": 21, "value": 2}, {"source": 10, "target": 23, "value": 2}, {"source": 10, "target": 24, "value": 2}, {"source": 16, "target": 2, "value": 2}, {"source": 16, "target": 15, "value": 2}]}