{"nodes": [{"id": "555364"}, {"id": "1004399"}, {"id": "1393316"}, {"id": "1219590"}, {"id": "123639"}, {"id": "1244689"}, {"id": "609246"}, {"id": "1105197"}, {"id": "1640572"}], "links": [{"source": 0, "target": 1, "value": 5}, {"source": 0, "target": 2, "value": 5}, {"source": 0, "target": 3, "value": 4}, {"source": 0, "target": 4, "value": 4}, {"source": 0, "target": 5, "value": 4}, {"source": 2, "target": 0, "value": 4}, {"source": 5, "target": 0, "value": 5}, {"source": 6, "target": 0, "value": 5}, {"source": 7, "target": 0, "value": 4}, {"source": 8, "target": 0, "value": 4}]}