{"nodes": [{"id": "235977"}, {"id": "332770"}, {"id": "1010732"}, {"id": "1023477"}, {"id": "1133806"}, {"id": "1142377"}, {"id": "1004399"}, {"id": "1818969"}, {"id": "1586611"}, {"id": "1001992"}, {"id": "1574638"}], "links": [{"source": 0, "target": 1, "value": 2}, {"source": 0, "target": 2, "value": 1}, {"source": 0, "target": 3, "value": 1}, {"source": 0, "target": 4, "value": 1}, {"source": 0, "target": 5, "value": 1}, {"source": 6, "target": 0, "value": 4}, {"source": 7, "target": 0, "value": 3}, {"source": 8, "target": 0, "value": 3}, {"source": 9, "target": 0, "value": 2}, {"source": 10, "target": 0, "value": 2}]}