{"nodes": [{"id": "external", "group": "20", "neighbors": []}, {"id": "416790", "group": "220", "neighbors": ["external"]}, {"id": "103653", "group": "1", "neighbors": ["external"]}, {"id": "1072283", "group": "1", "neighbors": ["external"]}, {"id": "1082533", "group": "35", "neighbors": ["219473", "external"]}, {"id": "1091843", "group": "8", "neighbors": ["1870006", "935851", "external"]}, {"id": "1096420", "group": "1", "neighbors": ["external"]}, {"id": "1127609", "group": "40", "neighbors": ["external"]}, {"id": "1217381", "group": "3", "neighbors": ["external"]}, {"id": "1220077", "group": "1", "neighbors": ["external"]}, {"id": "1232645", "group": "1", "neighbors": ["external"]}, {"id": "1301820", "group": "1", "neighbors": ["external"]}, {"id": "1322226", "group": "27", "neighbors": ["1223924", "1753321", "2026631", "835980", "external"]}, {"id": "1357765", "group": "315", "neighbors": ["external"]}, {"id": "1361849", "group": "1", "neighbors": ["external"]}, {"id": "1397828", "group": "1", "neighbors": ["external"]}, {"id": "1447331", "group": "1", "neighbors": ["external"]}, {"id": "1450164", "group": "3", "neighbors": ["external"]}, {"id": "1515770", "group": "32", "neighbors": ["external"]}, {"id": "1537207", "group": "22", "neighbors": ["484248", "external"]}, {"id": "1571610", "group": "36", "neighbors": ["941561", "external"]}, {"id": "1580679", "group": "5", "neighbors": ["external"]}, {"id": "1583686", "group": "95", "neighbors": ["external"]}, {"id": "1644402", "group": "15", "neighbors": ["external"]}, {"id": "1651203", "group": "1", "neighbors": ["external"]}, {"id": "168011", "group": "7", "neighbors": ["external"]}, {"id": "1683806", "group": "1", "neighbors": ["external"]}, {"id": "168789", "group": "1", "neighbors": ["external"]}, {"id": "1690345", "group": "1", "neighbors": ["external"]}, {"id": "1714092", "group": "1", "neighbors": ["external"]}, {"id": "1732683", "group": "205", "neighbors": ["external"]}, {"id": "17425", "group": "1", "neighbors": ["external"]}, {"id": "1753321", "group": "27", "neighbors": ["1223924", "1322226", "2026631", "835980", "external"]}, {"id": "1789765", "group": "38", "neighbors": ["external"]}, {"id": "1794987", "group": "9", "neighbors": ["external"]}, {"id": "1800174", "group": "14", "neighbors": ["external"]}, {"id": "1810521", "group": "7", "neighbors": ["168011", "external"]}, {"id": "1959300", "group": "11", "neighbors": ["external"]}, {"id": "1972355", "group": "37", "neighbors": ["external"]}, {"id": "2007364", "group": "2", "neighbors": ["external"]}, {"id": "2018366", "group": "126", "neighbors": ["external"]}, {"id": "2026631", "group": "27", "neighbors": ["external"]}, {"id": "219473", "group": "35", "neighbors": ["1082533", "external"]}, {"id": "227163", "group": "1", "neighbors": ["external"]}, {"id": "229683", "group": "1", "neighbors": ["external"]}, {"id": "307026", "group": "34", "neighbors": ["external"]}, {"id": "327024", "group": "43", "neighbors": ["external"]}, {"id": "346577", "group": "289", "neighbors": ["external"]}, {"id": "37720", "group": "1", "neighbors": ["external"]}, {"id": "428879", "group": "344", "neighbors": ["external"]}, {"id": "43833", "group": "1", "neighbors": ["external"]}, {"id": "439435", "group": "3", "neighbors": ["external"]}, {"id": "450381", "group": "7", "neighbors": ["external"]}, {"id": "484248", "group": "22", "neighbors": ["1537207", "external"]}, {"id": "511389", "group": "39", "neighbors": ["external"]}, {"id": "520054", "group": "292", "neighbors": ["external"]}, {"id": "526691", "group": "1", "neighbors": ["external"]}, {"id": "527615", "group": "1", "neighbors": ["external"]}, {"id": "569764", "group": "317", "neighbors": ["external"]}, {"id": "583339", "group": "14", "neighbors": ["external"]}, {"id": "60359", "group": "323", "neighbors": ["external"]}, {"id": "618380", "group": "298", "neighbors": ["external"]}, {"id": "62001", "group": "33", "neighbors": ["external"]}, {"id": "624375", "group": "1", "neighbors": ["external"]}, {"id": "628661", "group": "7", "neighbors": ["450381", "external"]}, {"id": "673087", "group": "276", "neighbors": ["external"]}, {"id": "676667", "group": "1", "neighbors": ["external"]}, {"id": "68697", "group": "302", "neighbors": ["external"]}, {"id": "692899", "group": "2", "neighbors": ["2007364", "external"]}, {"id": "711106", "group": "1", "neighbors": ["external"]}, {"id": "7157", "group": "47", "neighbors": ["external"]}, {"id": "772909", "group": "32", "neighbors": ["1515770", "external"]}, {"id": "810181", "group": "1", "neighbors": ["external"]}, {"id": "835980", "group": "27", "neighbors": ["1223924", "1322226", "1753321", "2026631", "external"]}, {"id": "869116", "group": "38", "neighbors": ["external"]}, {"id": "935851", "group": "8", "neighbors": ["1870006", "external"]}, {"id": "941561", "group": "36", "neighbors": ["external"]}, {"id": "976760", "group": "1", "neighbors": ["external"]}, {"id": "1006879", "group": "91", "neighbors": ["external"]}, {"id": "1061985", "group": "1", "neighbors": ["external"]}, {"id": "1085001", "group": "17", "neighbors": ["external"]}, {"id": "1107067", "group": "575", "neighbors": ["external"]}, {"id": "1118070", "group": "577", "neighbors": ["external"]}, {"id": "1140475", "group": "17", "neighbors": ["1085001", "108717", "1578380", "external"]}, {"id": "1149884", "group": "3", "neighbors": ["external"]}, {"id": "1151026", "group": "472", "neighbors": ["external"]}, {"id": "1157521", "group": "3", "neighbors": ["external"]}, {"id": "1159079", "group": "1", "neighbors": ["external"]}, {"id": "1219287", "group": "133", "neighbors": ["external"]}, {"id": "1223924", "group": "27", "neighbors": ["external"]}, {"id": "1243126", "group": "91", "neighbors": ["1494148", "external"]}, {"id": "1269418", "group": "38", "neighbors": ["external"]}, {"id": "1309149", "group": "109", "neighbors": ["external"]}, {"id": "1315406", "group": "4", "neighbors": ["external"]}, {"id": "1358860", "group": "15", "neighbors": ["external"]}, {"id": "1399218", "group": "73", "neighbors": ["external"]}, {"id": "1421396", "group": "10", "neighbors": ["external"]}, {"id": "149248", "group": "523", "neighbors": ["external"]}, {"id": "1517885", "group": "584", "neighbors": ["external"]}, {"id": "1526716", "group": "64", "neighbors": ["external"]}, {"id": "1590133", "group": "346", "neighbors": ["external"]}, {"id": "1601276", "group": "3", "neighbors": ["external"]}, {"id": "1648100", "group": "101", "neighbors": ["external"]}, {"id": "1669211", "group": "65", "neighbors": ["external"]}, {"id": "1702844", "group": "28", "neighbors": ["external"]}, {"id": "1711922", "group": "3", "neighbors": ["external"]}, {"id": "1731054", "group": "80", "neighbors": ["external"]}, {"id": "1731332", "group": "242", "neighbors": ["external"]}, {"id": "1761577", "group": "74", "neighbors": ["external"]}, {"id": "1870006", "group": "8", "neighbors": ["935851", "external"]}, {"id": "1890453", "group": "613", "neighbors": ["external"]}, {"id": "1925454", "group": "40", "neighbors": ["external"]}, {"id": "1975435", "group": "1", "neighbors": ["external"]}, {"id": "2001961", "group": "3", "neighbors": ["external"]}, {"id": "2010544", "group": "3", "neighbors": ["external"]}, {"id": "2039599", "group": "3", "neighbors": ["external"]}, {"id": "2041158", "group": "38", "neighbors": ["external"]}, {"id": "2091832", "group": "234", "neighbors": ["external"]}, {"id": "236252", "group": "37", "neighbors": ["external"]}, {"id": "325925", "group": "454", "neighbors": ["external"]}, {"id": "36486", "group": "14", "neighbors": ["583339", "external"]}, {"id": "371807", "group": "479", "neighbors": ["external"]}, {"id": "384461", "group": "34", "neighbors": ["external"]}, {"id": "401822", "group": "138", "neighbors": ["external"]}, {"id": "427006", "group": "344", "neighbors": ["external"]}, {"id": "435513", "group": "30", "neighbors": ["external"]}, {"id": "45157", "group": "42", "neighbors": ["external"]}, {"id": "453302", "group": "8", "neighbors": ["external"]}, {"id": "454814", "group": "199", "neighbors": ["external"]}, {"id": "464204", "group": "34", "neighbors": ["external"]}, {"id": "500084", "group": "3", "neighbors": ["external"]}, {"id": "57806", "group": "494", "neighbors": ["external"]}, {"id": "600044", "group": "255", "neighbors": ["external"]}, {"id": "727327", "group": "389", "neighbors": ["external"]}, {"id": "748719", "group": "29", "neighbors": ["external"]}, {"id": "768020", "group": "29", "neighbors": ["1849867", "346215", "748719", "external"]}, {"id": "773058", "group": "280", "neighbors": ["external"]}, {"id": "777486", "group": "46", "neighbors": ["external"]}, {"id": "805298", "group": "22", "neighbors": ["1537207", "484248", "external"]}, {"id": "873560", "group": "147", "neighbors": ["external"]}, {"id": "874468", "group": "24", "neighbors": ["external"]}, {"id": "931560", "group": "152", "neighbors": ["external"]}, {"id": "962522", "group": "3", "neighbors": ["external"]}, {"id": "96285", "group": "269", "neighbors": ["external"]}, {"id": "969256", "group": "3", "neighbors": ["external"]}, {"id": "971885", "group": "26", "neighbors": ["external"]}, {"id": "998575", "group": "515", "neighbors": ["external"]}, {"id": "207136", "group": "146", "neighbors": ["522711", "external"]}, {"id": "522711", "group": "146", "neighbors": ["207136", "external"]}, {"id": "723831", "group": "61", "neighbors": ["external"]}, {"id": "637018", "group": "144", "neighbors": ["external"]}, {"id": "1658699", "group": "157", "neighbors": ["723831", "external"]}, {"id": "1581087", "group": "2", "neighbors": ["external"]}, {"id": "379254", "group": "12", "neighbors": ["external"]}, {"id": "1468284", "group": "13", "neighbors": ["277532", "external"]}, {"id": "1368389", "group": "33", "neighbors": ["external"]}, {"id": "1007911", "group": "177", "neighbors": ["external"]}, {"id": "1008236", "group": "20", "neighbors": ["external"]}, {"id": "1305659", "group": "39", "neighbors": ["external"]}, {"id": "1486793", "group": "30", "neighbors": ["external"]}, {"id": "1013417", "group": "572", "neighbors": ["external"]}, {"id": "1406931", "group": "6", "neighbors": ["external"]}, {"id": "1058549", "group": "309", "neighbors": ["external"]}, {"id": "1070569", "group": "3", "neighbors": ["2007364", "external"]}, {"id": "1849867", "group": "29", "neighbors": ["748719", "external"]}, {"id": "1221080", "group": "21", "neighbors": ["external"]}, {"id": "1578380", "group": "17", "neighbors": ["1085001", "108717", "1140475", "external"]}, {"id": "108717", "group": "17", "neighbors": ["external"]}, {"id": "1634680", "group": "119", "neighbors": ["745214", "external"]}, {"id": "745214", "group": "119", "neighbors": ["external"]}, {"id": "369256", "group": "71", "neighbors": ["external"]}, {"id": "1484109", "group": "11", "neighbors": ["external"]}, {"id": "2061690", "group": "134", "neighbors": ["external"]}, {"id": "281945", "group": "67", "neighbors": ["external"]}, {"id": "1494148", "group": "52", "neighbors": ["external"]}, {"id": "1544975", "group": "5", "neighbors": ["external"]}, {"id": "1989874", "group": "238", "neighbors": ["external"]}, {"id": "346215", "group": "29", "neighbors": ["external"]}, {"id": "610092", "group": "145", "neighbors": ["external"]}, {"id": "277532", "group": "13", "neighbors": ["external"]}, {"id": "1534016", "group": "12", "neighbors": ["external"]}, {"id": "104120", "group": "1", "neighbors": ["external"]}, {"id": "514438", "group": "25", "neighbors": ["external"]}, {"id": "1046909", "group": "271", "neighbors": ["external"]}, {"id": "991560", "group": "30", "neighbors": ["external"]}, {"id": "2036628", "group": "13", "neighbors": ["external"]}, {"id": "579220", "group": "13", "neighbors": ["external"]}, {"id": "715273", "group": "386", "neighbors": ["external"]}, {"id": "1718759", "group": "10", "neighbors": ["1085001", "external"]}, {"id": "1750809", "group": "10", "neighbors": ["external"]}, {"id": "1766662", "group": "19", "neighbors": ["external"]}, {"id": "1180630", "group": "13", "neighbors": ["external"]}, {"id": "1053403", "group": "3", "neighbors": ["external"]}, {"id": "487752", "group": "400", "neighbors": ["external"]}, {"id": "1063806", "group": "363", "neighbors": ["external"]}, {"id": "524698", "group": "19", "neighbors": ["external"]}, {"id": "1738746", "group": "8", "neighbors": ["external"]}, {"id": "1078883", "group": "506", "neighbors": ["external"]}, {"id": "1792441", "group": "206", "neighbors": ["external"]}, {"id": "1760095", "group": "353", "neighbors": ["external"]}, {"id": "1441445", "group": "178", "neighbors": ["external"]}, {"id": "813863", "group": "3", "neighbors": ["external"]}, {"id": "845051", "group": "21", "neighbors": ["external"]}, {"id": "416647", "group": "140", "neighbors": ["external"]}, {"id": "1611783", "group": "180", "neighbors": ["external"]}, {"id": "1126403", "group": "694", "neighbors": ["external"]}, {"id": "304726", "group": "223", "neighbors": ["external"]}, {"id": "1571662", "group": "525", "neighbors": ["external"]}, {"id": "302897", "group": "22", "neighbors": ["external"]}, {"id": "816259", "group": "1", "neighbors": ["external"]}, {"id": "42803", "group": "139", "neighbors": ["external"]}, {"id": "1911656", "group": "1", "neighbors": ["external"]}, {"id": "1162853", "group": "432", "neighbors": ["external"]}, {"id": "1342989", "group": "241", "neighbors": ["external"]}, {"id": "118785", "group": "168", "neighbors": ["external"]}, {"id": "1323128", "group": "186", "neighbors": ["external"]}, {"id": "352434", "group": "283", "neighbors": ["external"]}, {"id": "401037", "group": "337", "neighbors": ["external"]}, {"id": "2027222", "group": "1", "neighbors": ["external"]}, {"id": "180277", "group": "1", "neighbors": ["external"]}, {"id": "443711", "group": "1", "neighbors": ["external"]}, {"id": "629314", "group": "352", "neighbors": ["external"]}, {"id": "526481", "group": "69", "neighbors": ["external"]}, {"id": "2096096", "group": "312", "neighbors": ["external"]}, {"id": "1369240", "group": "92", "neighbors": ["external"]}, {"id": "1367913", "group": "615", "neighbors": ["external"]}, {"id": "1606602", "group": "368", "neighbors": ["external"]}, {"id": "141459", "group": "168", "neighbors": ["external"]}, {"id": "141708", "group": "1", "neighbors": ["external"]}, {"id": "1479240", "group": "243", "neighbors": ["external"]}, {"id": "1574620", "group": "243", "neighbors": ["external"]}, {"id": "1424787", "group": "224", "neighbors": ["external"]}, {"id": "987495", "group": "3", "neighbors": ["external"]}, {"id": "1461139", "group": "3", "neighbors": ["external"]}, {"id": "1465836", "group": "3", "neighbors": ["external"]}, {"id": "1470439", "group": "13", "neighbors": ["external"]}, {"id": "1492555", "group": "30", "neighbors": ["external"]}, {"id": "576890", "group": "758", "neighbors": ["external"]}, {"id": "1515466", "group": "166", "neighbors": ["external"]}, {"id": "932809", "group": "630", "neighbors": ["external"]}, {"id": "1539142", "group": "1", "neighbors": ["external"]}, {"id": "1545631", "group": "3", "neighbors": ["external"]}, {"id": "989326", "group": "502", "neighbors": ["external"]}, {"id": "1567292", "group": "3", "neighbors": ["external"]}, {"id": "1598831", "group": "3", "neighbors": ["external"]}, {"id": "984014", "group": "318", "neighbors": ["external"]}, {"id": "1614842", "group": "726", "neighbors": ["external"]}, {"id": "1635849", "group": "544", "neighbors": ["external"]}, {"id": "163738", "group": "95", "neighbors": ["external"]}, {"id": "383773", "group": "245", "neighbors": ["external"]}, {"id": "1688901", "group": "452", "neighbors": ["external"]}, {"id": "73058", "group": "349", "neighbors": ["external"]}, {"id": "1822602", "group": "503", "neighbors": ["external"]}, {"id": "1836250", "group": "3", "neighbors": ["external"]}, {"id": "1898843", "group": "607", "neighbors": ["external"]}, {"id": "191538", "group": "601", "neighbors": ["external"]}, {"id": "886431", "group": "684", "neighbors": ["external"]}, {"id": "1982133", "group": "304", "neighbors": ["external"]}, {"id": "1994529", "group": "3", "neighbors": ["external"]}, {"id": "230971", "group": "265", "neighbors": ["external"]}, {"id": "292773", "group": "126", "neighbors": ["external"]}, {"id": "2031799", "group": "272", "neighbors": ["external"]}, {"id": "203354", "group": "743", "neighbors": ["external"]}, {"id": "2085269", "group": "645", "neighbors": ["external"]}, {"id": "725044", "group": "204", "neighbors": ["external"]}, {"id": "242353", "group": "89", "neighbors": ["external"]}, {"id": "249267", "group": "3", "neighbors": ["external"]}, {"id": "272033", "group": "20", "neighbors": ["external"]}, {"id": "896600", "group": "571", "neighbors": ["external"]}, {"id": "403432", "group": "3", "neighbors": ["external"]}, {"id": "421589", "group": "3", "neighbors": ["external"]}, {"id": "521692", "group": "666", "neighbors": ["external"]}, {"id": "539017", "group": "20", "neighbors": ["external"]}, {"id": "608152", "group": "20", "neighbors": ["external"]}, {"id": "669970", "group": "443", "neighbors": ["external"]}, {"id": "680685", "group": "439", "neighbors": ["external"]}, {"id": "732943", "group": "677", "neighbors": ["external"]}, {"id": "746567", "group": "409", "neighbors": ["external"]}, {"id": "827231", "group": "20", "neighbors": ["external"]}, {"id": "978147", "group": "1", "neighbors": ["external"]}], "links": [{"source": 1, "target": 0, "value": 2}, {"source": 2, "target": 0, "value": 2}, {"source": 3, "target": 0, "value": 3}, {"source": 4, "target": 42, "value": 3}, {"source": 4, "target": 0, "value": 2}, {"source": 5, "target": 109, "value": 3}, {"source": 5, "target": 75, "value": 3}, {"source": 5, "target": 0, "value": 2}, {"source": 6, "target": 0, "value": 2}, {"source": 7, "target": 0, "value": 2}, {"source": 8, "target": 0, "value": 14}, {"source": 9, "target": 0, "value": 2}, {"source": 10, "target": 0, "value": 2}, {"source": 11, "target": 0, "value": 2}, {"source": 12, "target": 89, "value": 3}, {"source": 12, "target": 32, "value": 3}, {"source": 12, "target": 41, "value": 3}, {"source": 12, "target": 73, "value": 3}, {"source": 12, "target": 0, "value": 2}, {"source": 13, "target": 0, "value": 2}, {"source": 14, "target": 0, "value": 3}, {"source": 15, "target": 0, "value": 2}, {"source": 16, "target": 0, "value": 2}, {"source": 17, "target": 0, "value": 2}, {"source": 18, "target": 0, "value": 3}, {"source": 19, "target": 53, "value": 2}, {"source": 19, "target": 0, "value": 2}, {"source": 20, "target": 76, "value": 2}, {"source": 20, "target": 0, "value": 2}, {"source": 21, "target": 0, "value": 2}, {"source": 22, "target": 0, "value": 2}, {"source": 23, "target": 0, "value": 2}, {"source": 24, "target": 0, "value": 2}, {"source": 25, "target": 0, "value": 3}, {"source": 26, "target": 0, "value": 2}, {"source": 27, "target": 0, "value": 2}, {"source": 28, "target": 0, "value": 3}, {"source": 29, "target": 0, "value": 2}, {"source": 30, "target": 0, "value": 2}, {"source": 31, "target": 0, "value": 2}, {"source": 32, "target": 89, "value": 3}, {"source": 32, "target": 12, "value": 3}, {"source": 32, "target": 41, "value": 3}, {"source": 32, "target": 73, "value": 2}, {"source": 32, "target": 0, "value": 2}, {"source": 33, "target": 0, "value": 2}, {"source": 34, "target": 0, "value": 2}, {"source": 35, "target": 0, "value": 2}, {"source": 36, "target": 25, "value": 2}, {"source": 36, "target": 0, "value": 2}, {"source": 37, "target": 0, "value": 2}, {"source": 38, "target": 0, "value": 2}, {"source": 39, "target": 0, "value": 2}, {"source": 40, "target": 0, "value": 2}, {"source": 41, "target": 0, "value": 2}, {"source": 42, "target": 4, "value": 2}, {"source": 42, "target": 0, "value": 2}, {"source": 43, "target": 0, "value": 2}, {"source": 44, "target": 0, "value": 2}, {"source": 45, "target": 0, "value": 2}, {"source": 46, "target": 0, "value": 2}, {"source": 47, "target": 0, "value": 2}, {"source": 48, "target": 0, "value": 2}, {"source": 49, "target": 0, "value": 2}, {"source": 50, "target": 0, "value": 2}, {"source": 51, "target": 0, "value": 2}, {"source": 52, "target": 0, "value": 2}, {"source": 53, "target": 19, "value": 4}, {"source": 53, "target": 0, "value": 2}, {"source": 54, "target": 0, "value": 2}, {"source": 55, "target": 0, "value": 2}, {"source": 56, "target": 0, "value": 3}, {"source": 57, "target": 0, "value": 2}, {"source": 58, "target": 0, "value": 2}, {"source": 59, "target": 0, "value": 2}, {"source": 60, "target": 0, "value": 2}, {"source": 61, "target": 0, "value": 2}, {"source": 62, "target": 0, "value": 2}, {"source": 63, "target": 0, "value": 2}, {"source": 64, "target": 52, "value": 3}, {"source": 64, "target": 0, "value": 2}, {"source": 65, "target": 0, "value": 2}, {"source": 66, "target": 0, "value": 2}, {"source": 67, "target": 0, "value": 2}, {"source": 68, "target": 39, "value": 2}, {"source": 68, "target": 0, "value": 2}, {"source": 69, "target": 0, "value": 2}, {"source": 70, "target": 0, "value": 3}, {"source": 71, "target": 18, "value": 2}, {"source": 71, "target": 0, "value": 2}, {"source": 72, "target": 0, "value": 2}, {"source": 73, "target": 89, "value": 2}, {"source": 73, "target": 12, "value": 2}, {"source": 73, "target": 32, "value": 2}, {"source": 73, "target": 41, "value": 2}, {"source": 73, "target": 0, "value": 2}, {"source": 74, "target": 0, "value": 2}, {"source": 75, "target": 109, "value": 2}, {"source": 75, "target": 0, "value": 3}, {"source": 76, "target": 0, "value": 2}, {"source": 77, "target": 0, "value": 2}, {"source": 78, "target": 0, "value": 3}, {"source": 79, "target": 0, "value": 2}, {"source": 80, "target": 0, "value": 2}, {"source": 81, "target": 0, "value": 2}, {"source": 82, "target": 0, "value": 3}, {"source": 83, "target": 80, "value": 2}, {"source": 83, "target": 167, "value": 2}, {"source": 83, "target": 166, "value": 2}, {"source": 83, "target": 0, "value": 2}, {"source": 84, "target": 0, "value": 9}, {"source": 85, "target": 0, "value": 2}, {"source": 86, "target": 0, "value": 2}, {"source": 87, "target": 0, "value": 3}, {"source": 88, "target": 0, "value": 2}, {"source": 89, "target": 0, "value": 2}, {"source": 90, "target": 174, "value": 2}, {"source": 90, "target": 0, "value": 2}, {"source": 91, "target": 0, "value": 2}, {"source": 92, "target": 0, "value": 2}, {"source": 93, "target": 0, "value": 2}, {"source": 94, "target": 0, "value": 2}, {"source": 95, "target": 0, "value": 2}, {"source": 96, "target": 0, "value": 2}, {"source": 97, "target": 0, "value": 2}, {"source": 98, "target": 0, "value": 2}, {"source": 99, "target": 0, "value": 2}, {"source": 100, "target": 0, "value": 2}, {"source": 101, "target": 0, "value": 9}, {"source": 102, "target": 0, "value": 2}, {"source": 103, "target": 0, "value": 2}, {"source": 104, "target": 0, "value": 2}, {"source": 105, "target": 0, "value": 6}, {"source": 106, "target": 0, "value": 2}, {"source": 107, "target": 0, "value": 2}, {"source": 108, "target": 0, "value": 3}, {"source": 109, "target": 75, "value": 2}, {"source": 109, "target": 0, "value": 2}, {"source": 110, "target": 0, "value": 2}, {"source": 111, "target": 0, "value": 2}, {"source": 112, "target": 0, "value": 2}, {"source": 113, "target": 0, "value": 3}, {"source": 114, "target": 0, "value": 2}, {"source": 115, "target": 0, "value": 2}, {"source": 116, "target": 0, "value": 2}, {"source": 117, "target": 0, "value": 2}, {"source": 118, "target": 0, "value": 2}, {"source": 119, "target": 0, "value": 2}, {"source": 120, "target": 59, "value": 3}, {"source": 120, "target": 0, "value": 3}, {"source": 121, "target": 0, "value": 2}, {"source": 122, "target": 0, "value": 2}, {"source": 123, "target": 0, "value": 3}, {"source": 124, "target": 0, "value": 2}, {"source": 125, "target": 0, "value": 2}, {"source": 126, "target": 0, "value": 2}, {"source": 127, "target": 0, "value": 2}, {"source": 128, "target": 0, "value": 2}, {"source": 129, "target": 0, "value": 2}, {"source": 130, "target": 0, "value": 2}, {"source": 131, "target": 0, "value": 2}, {"source": 132, "target": 0, "value": 2}, {"source": 133, "target": 0, "value": 2}, {"source": 134, "target": 0, "value": 2}, {"source": 135, "target": 164, "value": 2}, {"source": 135, "target": 177, "value": 2}, {"source": 135, "target": 134, "value": 2}, {"source": 135, "target": 0, "value": 2}, {"source": 136, "target": 0, "value": 2}, {"source": 137, "target": 0, "value": 2}, {"source": 138, "target": 19, "value": 2}, {"source": 138, "target": 53, "value": 2}, {"source": 138, "target": 0, "value": 2}, {"source": 139, "target": 0, "value": 2}, {"source": 140, "target": 0, "value": 2}, {"source": 141, "target": 0, "value": 2}, {"source": 142, "target": 0, "value": 2}, {"source": 143, "target": 0, "value": 2}, {"source": 144, "target": 0, "value": 2}, {"source": 145, "target": 0, "value": 3}, {"source": 146, "target": 0, "value": 2}, {"source": 147, "target": 148, "value": 4}, {"source": 147, "target": 0, "value": 2}, {"source": 148, "target": 147, "value": 3}, {"source": 148, "target": 0, "value": 2}, {"source": 149, "target": 0, "value": 2}, {"source": 150, "target": 0, "value": 3}, {"source": 151, "target": 149, "value": 2}, {"source": 151, "target": 0, "value": 2}, {"source": 152, "target": 0, "value": 3}, {"source": 153, "target": 0, "value": 2}, {"source": 154, "target": 179, "value": 2}, {"source": 154, "target": 0, "value": 2}, {"source": 155, "target": 0, "value": 2}, {"source": 156, "target": 0, "value": 2}, {"source": 157, "target": 0, "value": 2}, {"source": 158, "target": 0, "value": 2}, {"source": 159, "target": 0, "value": 2}, {"source": 160, "target": 0, "value": 2}, {"source": 161, "target": 0, "value": 2}, {"source": 162, "target": 0, "value": 2}, {"source": 163, "target": 39, "value": 2}, {"source": 163, "target": 0, "value": 2}, {"source": 164, "target": 134, "value": 2}, {"source": 164, "target": 0, "value": 2}, {"source": 165, "target": 0, "value": 2}, {"source": 166, "target": 80, "value": 3}, {"source": 166, "target": 167, "value": 3}, {"source": 166, "target": 83, "value": 2}, {"source": 166, "target": 0, "value": 2}, {"source": 167, "target": 0, "value": 2}, {"source": 168, "target": 169, "value": 2}, {"source": 168, "target": 0, "value": 2}, {"source": 169, "target": 0, "value": 2}, {"source": 170, "target": 0, "value": 2}, {"source": 171, "target": 0, "value": 2}, {"source": 172, "target": 0, "value": 2}, {"source": 173, "target": 0, "value": 2}, {"source": 174, "target": 0, "value": 2}, {"source": 175, "target": 0, "value": 2}, {"source": 176, "target": 0, "value": 2}, {"source": 177, "target": 0, "value": 2}, {"source": 178, "target": 0, "value": 2}, {"source": 179, "target": 0, "value": 3}, {"source": 180, "target": 0, "value": 2}, {"source": 181, "target": 0, "value": 2}, {"source": 182, "target": 0, "value": 2}, {"source": 183, "target": 0, "value": 2}, {"source": 184, "target": 0, "value": 2}, {"source": 185, "target": 0, "value": 2}, {"source": 186, "target": 0, "value": 2}, {"source": 187, "target": 0, "value": 3}, {"source": 188, "target": 80, "value": 2}, {"source": 188, "target": 0, "value": 2}, {"source": 189, "target": 0, "value": 2}, {"source": 190, "target": 0, "value": 2}, {"source": 191, "target": 0, "value": 2}, {"source": 192, "target": 0, "value": 3}, {"source": 193, "target": 0, "value": 2}, {"source": 194, "target": 0, "value": 2}, {"source": 195, "target": 0, "value": 2}, {"source": 196, "target": 0, "value": 2}, {"source": 197, "target": 0, "value": 2}, {"source": 198, "target": 0, "value": 2}, {"source": 199, "target": 0, "value": 2}, {"source": 200, "target": 0, "value": 2}, {"source": 201, "target": 0, "value": 2}, {"source": 202, "target": 0, "value": 2}, {"source": 203, "target": 0, "value": 2}, {"source": 204, "target": 0, "value": 2}, {"source": 205, "target": 0, "value": 3}, {"source": 206, "target": 0, "value": 2}, {"source": 207, "target": 0, "value": 2}, {"source": 208, "target": 0, "value": 3}, {"source": 209, "target": 0, "value": 2}, {"source": 210, "target": 0, "value": 2}, {"source": 211, "target": 0, "value": 2}, {"source": 212, "target": 0, "value": 2}, {"source": 213, "target": 0, "value": 2}, {"source": 214, "target": 0, "value": 2}, {"source": 215, "target": 0, "value": 2}, {"source": 216, "target": 0, "value": 2}, {"source": 217, "target": 0, "value": 2}, {"source": 218, "target": 0, "value": 2}, {"source": 219, "target": 0, "value": 2}, {"source": 220, "target": 0, "value": 2}, {"source": 221, "target": 0, "value": 2}, {"source": 222, "target": 0, "value": 2}, {"source": 223, "target": 0, "value": 2}, {"source": 224, "target": 0, "value": 2}, {"source": 225, "target": 0, "value": 2}, {"source": 226, "target": 0, "value": 2}, {"source": 227, "target": 0, "value": 2}, {"source": 228, "target": 0, "value": 2}, {"source": 229, "target": 0, "value": 2}, {"source": 230, "target": 0, "value": 2}, {"source": 231, "target": 0, "value": 2}, {"source": 232, "target": 0, "value": 2}, {"source": 233, "target": 0, "value": 2}, {"source": 234, "target": 0, "value": 2}, {"source": 235, "target": 0, "value": 2}, {"source": 236, "target": 0, "value": 2}, {"source": 237, "target": 0, "value": 2}, {"source": 238, "target": 0, "value": 2}, {"source": 239, "target": 0, "value": 2}, {"source": 240, "target": 0, "value": 2}, {"source": 241, "target": 0, "value": 2}, {"source": 242, "target": 0, "value": 2}, {"source": 243, "target": 0, "value": 2}, {"source": 244, "target": 0, "value": 2}, {"source": 245, "target": 0, "value": 2}, {"source": 246, "target": 0, "value": 2}, {"source": 247, "target": 0, "value": 2}, {"source": 248, "target": 0, "value": 2}, {"source": 249, "target": 0, "value": 3}, {"source": 250, "target": 0, "value": 2}, {"source": 251, "target": 0, "value": 2}, {"source": 252, "target": 0, "value": 2}, {"source": 253, "target": 0, "value": 2}, {"source": 254, "target": 0, "value": 2}, {"source": 255, "target": 0, "value": 2}, {"source": 256, "target": 0, "value": 2}, {"source": 257, "target": 0, "value": 2}, {"source": 258, "target": 0, "value": 2}, {"source": 259, "target": 0, "value": 2}, {"source": 260, "target": 0, "value": 2}, {"source": 261, "target": 0, "value": 2}, {"source": 262, "target": 0, "value": 3}, {"source": 263, "target": 0, "value": 2}, {"source": 264, "target": 0, "value": 2}, {"source": 265, "target": 0, "value": 2}, {"source": 266, "target": 0, "value": 2}, {"source": 267, "target": 0, "value": 2}, {"source": 268, "target": 0, "value": 2}, {"source": 269, "target": 0, "value": 2}, {"source": 270, "target": 0, "value": 2}, {"source": 271, "target": 0, "value": 2}, {"source": 272, "target": 0, "value": 2}, {"source": 273, "target": 0, "value": 2}, {"source": 274, "target": 0, "value": 2}, {"source": 275, "target": 0, "value": 2}, {"source": 276, "target": 0, "value": 2}, {"source": 277, "target": 0, "value": 3}, {"source": 278, "target": 0, "value": 2}, {"source": 279, "target": 0, "value": 2}]}