{"nodes": [{"id": "1536579"}, {"id": "1376839"}, {"id": "285969"}, {"id": "830269"}, {"id": "1426264"}, {"id": "1469128"}, {"id": "1768688"}, {"id": "246969"}, {"id": "445984"}, {"id": "1149129"}, {"id": "1382309"}], "links": [{"source": 0, "target": 1, "value": 3}, {"source": 0, "target": 2, "value": 3}, {"source": 0, "target": 3, "value": 3}, {"source": 0, "target": 4, "value": 2}, {"source": 0, "target": 5, "value": 2}, {"source": 6, "target": 0, "value": 5}, {"source": 7, "target": 0, "value": 4}, {"source": 8, "target": 0, "value": 3}, {"source": 9, "target": 0, "value": 3}, {"source": 10, "target": 0, "value": 3}]}