{"nodes": [{"id": "445984"}, {"id": "1050842"}, {"id": "1138370"}, {"id": "1152015"}, {"id": "1152794"}, {"id": "1180493"}, {"id": "1149129"}, {"id": "1544108"}, {"id": "1706585"}, {"id": "482636"}], "links": [{"source": 0, "target": 1, "value": 4}, {"source": 0, "target": 2, "value": 4}, {"source": 0, "target": 3, "value": 4}, {"source": 0, "target": 4, "value": 4}, {"source": 0, "target": 5, "value": 4}, {"source": 4, "target": 0, "value": 2}, {"source": 6, "target": 0, "value": 2}, {"source": 7, "target": 0, "value": 2}, {"source": 8, "target": 0, "value": 2}, {"source": 9, "target": 0, "value": 2}]}