{"nodes": [{"id": "439435", "neighbors": ["1278894"]}, {"id": "1278894", "neighbors": ["1102428", "1228230", "1535918", "1640943", "1643702", "1678214", "241608", "429404", "439435", "502803", "824420", "931011"]}, {"id": "1161861", "neighbors": []}, {"id": "1768688", "neighbors": []}, {"id": "732739", "neighbors": ["661368", "748719"]}, {"id": "449362", "neighbors": []}, {"id": "1096872", "neighbors": []}, {"id": "661368", "neighbors": []}, {"id": "185956", "neighbors": ["1102428", "1768688"]}, {"id": "824420", "neighbors": ["1278894"]}, {"id": "444898", "neighbors": ["1096872", "1161861", "1376114", "1643702", "429404", "439435"]}, {"id": "1102428", "neighbors": ["1278894", "1768688", "185956", "748719"]}, {"id": "86940", "neighbors": []}, {"id": "931011", "neighbors": ["1278894", "429404"]}, {"id": "748719", "neighbors": ["1678214", "824420"]}, {"id": "1168991", "neighbors": ["1228230", "1535918", "1643702", "1766909", "502803"]}, {"id": "1643702", "neighbors": ["1168991", "1228230", "1278894", "1535918", "21979", "241608", "444898", "449362", "502803"]}, {"id": "116446", "neighbors": []}, {"id": "1228230", "neighbors": ["1278894"]}, {"id": "1376114", "neighbors": ["241608"]}, {"id": "1535918", "neighbors": ["1168991", "1228230", "1278894", "1643702", "502803"]}, {"id": "1640943", "neighbors": ["1278894"]}, {"id": "1766909", "neighbors": []}, {"id": "1803705", "neighbors": []}, {"id": "21979", "neighbors": []}, {"id": "241608", "neighbors": ["1278894", "1376114"]}, {"id": "384714", "neighbors": []}, {"id": "429404", "neighbors": ["1278894", "384714"]}, {"id": "502803", "neighbors": ["1278894"]}, {"id": "68027", "neighbors": []}, {"id": "1678214", "neighbors": ["1278894"]}], "links": [{"source": 0, "target": 1, "value": 5}, {"source": 1, "target": 11, "value": 10}, {"source": 1, "target": 18, "value": 11}, {"source": 1, "target": 20, "value": 11}, {"source": 1, "target": 21, "value": 11}, {"source": 1, "target": 16, "value": 11}, {"source": 1, "target": 30, "value": 12}, {"source": 1, "target": 25, "value": 5}, {"source": 1, "target": 27, "value": 4}, {"source": 1, "target": 0, "value": 6}, {"source": 1, "target": 28, "value": 11}, {"source": 1, "target": 9, "value": 12}, {"source": 1, "target": 13, "value": 5}, {"source": 4, "target": 7, "value": 2}, {"source": 4, "target": 14, "value": 2}, {"source": 8, "target": 11, "value": 4}, {"source": 8, "target": 3, "value": 2}, {"source": 9, "target": 1, "value": 12}, {"source": 10, "target": 6, "value": 3}, {"source": 10, "target": 2, "value": 3}, {"source": 10, "target": 19, "value": 2}, {"source": 10, "target": 16, "value": 2}, {"source": 10, "target": 27, "value": 2}, {"source": 10, "target": 0, "value": 2}, {"source": 11, "target": 1, "value": 10}, {"source": 11, "target": 3, "value": 2}, {"source": 11, "target": 8, "value": 4}, {"source": 11, "target": 14, "value": 2}, {"source": 13, "target": 1, "value": 5}, {"source": 13, "target": 27, "value": 2}, {"source": 14, "target": 30, "value": 2}, {"source": 14, "target": 9, "value": 2}, {"source": 15, "target": 18, "value": 2}, {"source": 15, "target": 20, "value": 2}, {"source": 15, "target": 16, "value": 2}, {"source": 15, "target": 22, "value": 2}, {"source": 15, "target": 28, "value": 3}, {"source": 16, "target": 15, "value": 2}, {"source": 16, "target": 18, "value": 3}, {"source": 16, "target": 1, "value": 11}, {"source": 16, "target": 20, "value": 2}, {"source": 16, "target": 24, "value": 2}, {"source": 16, "target": 25, "value": 2}, {"source": 16, "target": 10, "value": 2}, {"source": 16, "target": 5, "value": 2}, {"source": 16, "target": 28, "value": 2}, {"source": 18, "target": 1, "value": 11}, {"source": 19, "target": 25, "value": 2}, {"source": 20, "target": 15, "value": 3}, {"source": 20, "target": 18, "value": 3}, {"source": 20, "target": 1, "value": 10}, {"source": 20, "target": 16, "value": 3}, {"source": 20, "target": 28, "value": 3}, {"source": 21, "target": 1, "value": 11}, {"source": 25, "target": 1, "value": 5}, {"source": 25, "target": 19, "value": 2}, {"source": 27, "target": 1, "value": 4}, {"source": 27, "target": 26, "value": 2}, {"source": 28, "target": 1, "value": 11}, {"source": 30, "target": 1, "value": 12}]}