{"nodes": [{"id": "1796799"}, {"id": "1278894"}, {"id": "1180630"}, {"id": "1361519"}, {"id": "1428078"}, {"id": "1588833"}, {"id": "964113"}, {"id": "896787"}, {"id": "549850"}, {"id": "1977815"}], "links": [{"source": 0, "target": 1, "value": 8}, {"source": 0, "target": 2, "value": 1}, {"source": 0, "target": 3, "value": 1}, {"source": 0, "target": 4, "value": 1}, {"source": 0, "target": 5, "value": 1}, {"source": 1, "target": 0, "value": 9}, {"source": 6, "target": 0, "value": 3}, {"source": 7, "target": 0, "value": 3}, {"source": 8, "target": 0, "value": 2}, {"source": 9, "target": 0, "value": 2}]}